{
    "config": {
        "max_coordinate": 1000
    },
    "nodes": 20,
    "node_positions": [
        [
            554,
            598
        ],
        [
            149,
            970
        ],
        [
            786,
            221
        ],
        [
            530,
            567
        ],
        [
            628,
            650
        ],
        [
            166,
            888
        ],
        [
            63,
            186
        ],
        [
            533,
            260
        ],
        [
            482,
            187
        ],
        [
            251,
            221
        ],
        [
            265,
            869
        ],
        [
            537,
            428
        ],
        [
            384,
            350
        ],
        [
            746,
            873
        ],
        [
            376,
            120
        ],
        [
            74,
            703
        ],
        [
            859,
            637
        ],
        [
            684,
            553
        ],
        [
            876,
            119
        ],
        [
            999,
            662
        ]
    ],
    "dist": [
        [
            0,
            549,
            442,
            39,
            90,
            484,
            640,
            338,
            417,
            483,
            396,
            170,
            300,
            335,
            510,
            491,
            307,
            137,
            577,
            449
        ],
        [
            549,
            0,
            983,
            554,
            576,
            83,
            788,
            807,
            850,
            755,
            153,
            666,
            663,
            604,
            879,
            277,
            784,
            678,
            1119,
            904
        ],
        [
            442,
            983,
            0,
            430,
            457,
            910,
            723,
            255,
            305,
            535,
            831,
            323,
            422,
            653,
            422,
            859,
            422,
            347,
            136,
            489
        ],
        [
            39,
            554,
            430,
            0,
            128,
            485,
            602,
            307,
            383,
            444,
            401,
            139,
            261,
            374,
            472,
            475,
            336,
            154,
            566,
            478
        ],
        [
            90,
            576,
            457,
            128,
            0,
            519,
            731,
            401,
            485,
            571,
            423,
            239,
            386,
            252,
            586,
            556,
            231,
            112,
            586,
            371
        ],
        [
            484,
            83,
            910,
            485,
            519,
            0,
            709,
            727,
            768,
            672,
            100,
            590,
            580,
            580,
            796,
            206,
            737,
            616,
            1046,
            863
        ],
        [
            640,
            788,
            723,
            602,
            731,
            709,
            0,
            475,
            419,
            191,
            712,
            532,
            360,
            968,
            319,
            517,
            914,
            721,
            815,
            1050
        ],
        [
            338,
            807,
            255,
            307,
            401,
            727,
            475,
            0,
            89,
            284,
            665,
            168,
            174,
            648,
            210,
            637,
            498,
            329,
            370,
            615
        ],
        [
            417,
            850,
            305,
            383,
            485,
            768,
            419,
            89,
            0,
            233,
            715,
            247,
            190,
            735,
            125,
            657,
            587,
            418,
            399,
            702
        ],
        [
            483,
            755,
            535,
            444,
            571,
            672,
            191,
            284,
            233,
            0,
            648,
            353,
            185,
            818,
            160,
            513,
            736,
            545,
            633,
            868
        ],
        [
            396,
            153,
            831,
            401,
            423,
            100,
            712,
            665,
            715,
            648,
            0,
            518,
            532,
            481,
            757,
            253,
            637,
            524,
            967,
            762
        ],
        [
            170,
            666,
            323,
            139,
            239,
            590,
            532,
            168,
            247,
            353,
            518,
            0,
            171,
            491,
            347,
            538,
            383,
            192,
            458,
            517
        ],
        [
            300,
            663,
            422,
            261,
            386,
            580,
            360,
            174,
            190,
            185,
            532,
            171,
            0,
            636,
            230,
            469,
            554,
            362,
            543,
            689
        ],
        [
            335,
            604,
            653,
            374,
            252,
            580,
            968,
            648,
            735,
            818,
            481,
            491,
            636,
            0,
            838,
            693,
            261,
            325,
            765,
            329
        ],
        [
            510,
            879,
            422,
            472,
            586,
            796,
            319,
            210,
            125,
            160,
            757,
            347,
            230,
            838,
            0,
            656,
            707,
            531,
            500,
            825
        ],
        [
            491,
            277,
            859,
            475,
            556,
            206,
            517,
            637,
            657,
            513,
            253,
            538,
            469,
            693,
            656,
            0,
            787,
            628,
            992,
            925
        ],
        [
            307,
            784,
            422,
            336,
            231,
            737,
            914,
            498,
            587,
            736,
            637,
            383,
            554,
            261,
            707,
            787,
            0,
            194,
            518,
            142
        ],
        [
            137,
            678,
            347,
            154,
            112,
            616,
            721,
            329,
            418,
            545,
            524,
            192,
            362,
            325,
            531,
            628,
            194,
            0,
            474,
            333
        ],
        [
            577,
            1119,
            136,
            566,
            586,
            1046,
            815,
            370,
            399,
            633,
            967,
            458,
            543,
            765,
            500,
            992,
            518,
            474,
            0,
            556
        ],
        [
            449,
            904,
            489,
            478,
            371,
            863,
            1050,
            615,
            702,
            868,
            762,
            517,
            689,
            329,
            825,
            925,
            142,
            333,
            556,
            0
        ]
    ]
}