{
    "config": {
        "max_coordinate": 1000
    },
    "nodes": 50,
    "node_positions": [
        [
            184,
            980
        ],
        [
            779,
            942
        ],
        [
            429,
            42
        ],
        [
            146,
            889
        ],
        [
            927,
            819
        ],
        [
            494,
            626
        ],
        [
            590,
            929
        ],
        [
            37,
            381
        ],
        [
            80,
            617
        ],
        [
            1,
            360
        ],
        [
            196,
            325
        ],
        [
            887,
            230
        ],
        [
            530,
            344
        ],
        [
            720,
            59
        ],
        [
            752,
            878
        ],
        [
            965,
            482
        ],
        [
            367,
            768
        ],
        [
            613,
            253
        ],
        [
            601,
            947
        ],
        [
            471,
            755
        ],
        [
            518,
            272
        ],
        [
            580,
            915
        ],
        [
            253,
            410
        ],
        [
            965,
            741
        ],
        [
            410,
            256
        ],
        [
            469,
            388
        ],
        [
            396,
            111
        ],
        [
            860,
            856
        ],
        [
            964,
            913
        ],
        [
            360,
            789
        ],
        [
            584,
            12
        ],
        [
            432,
            112
        ],
        [
            222,
            873
        ],
        [
            945,
            191
        ],
        [
            252,
            172
        ],
        [
            740,
            609
        ],
        [
            74,
            904
        ],
        [
            480,
            546
        ],
        [
            713,
            302
        ],
        [
            850,
            771
        ],
        [
            582,
            938
        ],
        [
            328,
            103
        ],
        [
            903,
            450
        ],
        [
            913,
            64
        ],
        [
            304,
            655
        ],
        [
            352,
            671
        ],
        [
            40,
            536
        ],
        [
            931,
            372
        ],
        [
            509,
            850
        ],
        [
            387,
            796
        ]
    ],
    "dist": [
        [
            0,
            596,
            969,
            98,
            760,
            470,
            409,
            616,
            377,
            646,
            655,
            1027,
            724,
            1065,
            577,
            926,
            280,
            844,
            418,
            364,
            782,
            401,
            574,
            816,
            758,
            657,
            894,
            687,
            782,
            259,
            1047,
            902,
            113,
            1096,
            810,
            668,
            133,
            525,
            859,
            698,
            400,
            888,
            893,
            1170,
            346,
            351,
            466,
            963,
            350,
            273
        ],
        [
            596,
            0,
            965,
            635,
            192,
            425,
            189,
            930,
            770,
            971,
            848,
            720,
            647,
            884,
            69,
            496,
            447,
            708,
            178,
            360,
            719,
            200,
            748,
            273,
            778,
            634,
            915,
            118,
            187,
            446,
            950,
            899,
            561,
            769,
            933,
            335,
            706,
            496,
            643,
            185,
            197,
            952,
            507,
            888,
            554,
            505,
            843,
            589,
            285,
            418
        ],
        [
            969,
            965,
            0,
            893,
            922,
            587,
            901,
            518,
            672,
            533,
            366,
            495,
            318,
            291,
            896,
            693,
            728,
            279,
            921,
            714,
            246,
            885,
            407,
            880,
            214,
            348,
            76,
            921,
            1022,
            750,
            157,
            70,
            856,
            537,
            219,
            646,
            932,
            506,
            385,
            841,
            908,
            117,
            625,
            484,
            625,
            633,
            628,
            600,
            811,
            755
        ],
        [
            98,
            635,
            893,
            0,
            784,
            436,
            445,
            519,
            279,
            548,
            566,
            991,
            666,
            1009,
            606,
            914,
            251,
            789,
            458,
            351,
            720,
            434,
            490,
            832,
            685,
            596,
            817,
            714,
            818,
            236,
            980,
            827,
            77,
            1060,
            724,
            656,
            73,
            478,
            816,
            713,
            438,
            806,
            875,
            1126,
            282,
            299,
            368,
            939,
            365,
            258
        ],
        [
            760,
            192,
            922,
            784,
            0,
            474,
            354,
            991,
            870,
            1033,
            882,
            590,
            619,
            787,
            184,
            339,
            562,
            647,
            350,
            460,
            683,
            360,
            788,
            86,
            764,
            628,
            885,
            76,
            101,
            567,
            876,
            863,
            707,
            628,
            935,
            281,
            857,
            523,
            559,
            90,
            364,
            933,
            369,
            755,
            644,
            593,
            931,
            447,
            419,
            540
        ],
        [
            470,
            425,
            587,
            436,
            474,
            0,
            317,
            518,
            414,
            560,
            423,
            557,
            284,
            610,
            360,
            492,
            190,
            391,
            338,
            131,
            354,
            301,
            323,
            484,
            379,
            239,
            524,
            432,
            550,
            211,
            620,
            517,
            367,
            626,
            514,
            246,
            503,
            81,
            391,
            384,
            324,
            548,
            445,
            701,
            192,
            148,
            462,
            505,
            224,
            200
        ],
        [
            409,
            189,
            901,
            445,
            354,
            317,
            0,
            778,
            597,
            818,
            721,
            759,
            588,
            879,
            169,
            583,
            275,
            676,
            21,
            210,
            660,
            17,
            618,
            419,
            696,
            554,
            840,
            279,
            374,
            269,
            917,
            832,
            372,
            818,
            829,
            353,
            516,
            398,
            638,
            304,
            12,
            866,
            572,
            923,
            396,
            351,
            675,
            653,
            113,
            242
        ],
        [
            616,
            930,
            518,
            519,
            991,
            518,
            778,
            0,
            239,
            41,
            168,
            863,
            494,
            755,
            870,
            933,
            508,
            590,
            799,
            572,
            493,
            761,
            217,
            995,
            393,
            432,
            449,
            950,
            1068,
            520,
            659,
            477,
            525,
            927,
            299,
            739,
            524,
            472,
            680,
            901,
            779,
            402,
            868,
            931,
            382,
            428,
            155,
            894,
            665,
            542
        ],
        [
            377,
            770,
            672,
            279,
            870,
            414,
            597,
            239,
            0,
            268,
            314,
            894,
            526,
            849,
            720,
            895,
            324,
            645,
            616,
            414,
            557,
            582,
            269,
            893,
            489,
            451,
            596,
            815,
            932,
            328,
            787,
            615,
            292,
            964,
            477,
            660,
            287,
            406,
            707,
            785,
            595,
            570,
            839,
            999,
            227,
            277,
            90,
            885,
            488,
            355
        ],
        [
            646,
            971,
            533,
            548,
            1033,
            560,
            818,
            41,
            268,
            0,
            198,
            895,
            529,
            779,
            912,
            971,
            548,
            621,
            839,
            613,
            524,
            802,
            256,
            1036,
            422,
            468,
            466,
            991,
            1110,
            559,
            678,
            497,
            558,
            959,
            313,
            779,
            548,
            513,
            714,
            943,
            819,
            415,
            906,
            958,
            422,
            468,
            180,
            930,
            705,
            582
        ],
        [
            655,
            848,
            366,
            566,
            882,
            423,
            721,
            168,
            314,
            198,
            0,
            697,
            334,
            587,
            784,
            784,
            474,
            423,
            742,
            510,
            326,
            703,
            102,
            874,
            224,
            280,
            292,
            850,
            967,
            492,
            498,
            317,
            548,
            760,
            162,
            613,
            591,
            359,
            517,
            791,
            724,
            258,
            717,
            763,
            347,
            379,
            262,
            736,
            611,
            508
        ],
        [
            1027,
            720,
            495,
            991,
            590,
            557,
            759,
            863,
            894,
            895,
            697,
            0,
            374,
            239,
            661,
            263,
            748,
            274,
            771,
            669,
            371,
            750,
            659,
            516,
            477,
            446,
            505,
            626,
            687,
            768,
            373,
            470,
            925,
            69,
            637,
            406,
            1056,
            515,
            188,
            542,
            770,
            573,
            220,
            168,
            721,
            693,
            900,
            148,
            726,
            755
        ],
        [
            724,
            647,
            318,
            666,
            619,
            284,
            588,
            494,
            526,
            529,
            334,
            374,
            0,
            342,
            578,
            456,
            454,
            123,
            607,
            415,
            72,
            573,
            284,
            588,
            148,
            75,
            268,
            609,
            715,
            476,
            336,
            251,
            612,
            442,
            326,
            338,
            722,
            208,
            187,
            533,
            596,
            314,
            387,
            474,
            384,
            372,
            526,
            401,
            506,
            474
        ],
        [
            1065,
            884,
            291,
            1009,
            787,
            610,
            879,
            755,
            849,
            779,
            587,
            239,
            342,
            0,
            819,
            488,
            792,
            221,
            895,
            739,
            293,
            867,
            584,
            724,
            367,
            413,
            328,
            809,
            888,
            813,
            143,
            292,
            954,
            260,
            481,
            550,
            1063,
            542,
            243,
            723,
            889,
            394,
            431,
            193,
            726,
            714,
            830,
            377,
            818,
            808
        ],
        [
            577,
            69,
            896,
            606,
            184,
            360,
            169,
            870,
            720,
            912,
            784,
            661,
            578,
            819,
            0,
            449,
            400,
            640,
            166,
            306,
            649,
            175,
            684,
            253,
            709,
            565,
            845,
            110,
            214,
            401,
            882,
            830,
            530,
            713,
            865,
            269,
            678,
            429,
            577,
            145,
            180,
            883,
            453,
            829,
            500,
            450,
            789,
            536,
            244,
            374
        ],
        [
            926,
            496,
            693,
            914,
            339,
            492,
            583,
            933,
            895,
            971,
            784,
            263,
            456,
            488,
            449,
            0,
            662,
            419,
            590,
            564,
            493,
            579,
            715,
            259,
            599,
            504,
            679,
            388,
            431,
            678,
            605,
            648,
            839,
            291,
            777,
            258,
            985,
            489,
            309,
            311,
            595,
            741,
            69,
            421,
            683,
            641,
            926,
            115,
            585,
            657
        ],
        [
            280,
            447,
            728,
            251,
            562,
            190,
            275,
            508,
            324,
            548,
            474,
            748,
            454,
            792,
            400,
            662,
            0,
            570,
            294,
            104,
            518,
            258,
            375,
            598,
            513,
            393,
            657,
            500,
            614,
            22,
            786,
            659,
            179,
            816,
            606,
            405,
            323,
            249,
            580,
            483,
            274,
            666,
            623,
            890,
            129,
            98,
            400,
            689,
            163,
            34
        ],
        [
            844,
            708,
            279,
            789,
            647,
            391,
            676,
            590,
            645,
            621,
            423,
            274,
            123,
            221,
            640,
            419,
            570,
            0,
            694,
            521,
            96,
            662,
            392,
            601,
            203,
            197,
            259,
            651,
            747,
            592,
            242,
            229,
            732,
            337,
            369,
            377,
            845,
            321,
            111,
            569,
            685,
            322,
            350,
            354,
            507,
            492,
            639,
            339,
            605,
            588
        ],
        [
            418,
            178,
            921,
            458,
            350,
            338,
            21,
            799,
            616,
            839,
            742,
            771,
            607,
            895,
            166,
            590,
            294,
            694,
            0,
            231,
            680,
            38,
            639,
            418,
            716,
            574,
            860,
            274,
            364,
            288,
            935,
            851,
            386,
            830,
            849,
            365,
            528,
            418,
            654,
            304,
            21,
            887,
            581,
            936,
            416,
            371,
            695,
            662,
            133,
            261
        ],
        [
            364,
            360,
            714,
            351,
            460,
            131,
            210,
            572,
            414,
            613,
            510,
            669,
            415,
            739,
            306,
            564,
            104,
            521,
            231,
            0,
            485,
            193,
            408,
            494,
            502,
            367,
            648,
            401,
            517,
            116,
            751,
            644,
            275,
            736,
            622,
            306,
            424,
            209,
            513,
            379,
            214,
            667,
            528,
            820,
            194,
            145,
            483,
            598,
            102,
            93
        ],
        [
            782,
            719,
            246,
            720,
            683,
            354,
            660,
            493,
            557,
            524,
            326,
            371,
            72,
            293,
            649,
            493,
            518,
            96,
            680,
            485,
            0,
            645,
            298,
            647,
            109,
            125,
            202,
            676,
            780,
            540,
            268,
            181,
            669,
            434,
            284,
            403,
            772,
            276,
            197,
            599,
            669,
            254,
            424,
            446,
            438,
            432,
            546,
            424,
            578,
            540
        ],
        [
            401,
            200,
            885,
            434,
            360,
            301,
            17,
            761,
            582,
            802,
            703,
            750,
            573,
            867,
            175,
            579,
            258,
            662,
            38,
            193,
            645,
            0,
            601,
            422,
            680,
            538,
            824,
            286,
            384,
            253,
            903,
            816,
            360,
            810,
            812,
            345,
            506,
            382,
            627,
            306,
            23,
            850,
            566,
            913,
            379,
            333,
            659,
            646,
            96,
            226
        ],
        [
            574,
            748,
            407,
            490,
            788,
            323,
            618,
            217,
            269,
            256,
            102,
            659,
            284,
            584,
            684,
            715,
            375,
            392,
            639,
            408,
            298,
            601,
            0,
            785,
            219,
            217,
            331,
            753,
            870,
            393,
            517,
            347,
            464,
            725,
            238,
            526,
            525,
            264,
            472,
            697,
            622,
            316,
            651,
            745,
            250,
            279,
            247,
            679,
            509,
            408
        ],
        [
            816,
            273,
            880,
            832,
            86,
            484,
            419,
            995,
            893,
            1036,
            874,
            516,
            588,
            724,
            253,
            259,
            598,
            601,
            418,
            494,
            647,
            422,
            785,
            0,
            737,
            608,
            848,
            155,
            172,
            606,
            822,
            824,
            754,
            550,
            912,
            260,
            905,
            522,
            506,
            118,
            430,
            901,
            297,
            678,
            666,
            616,
            947,
            370,
            468,
            580
        ],
        [
            758,
            778,
            214,
            685,
            764,
            379,
            696,
            393,
            489,
            422,
            224,
            477,
            148,
            367,
            709,
            599,
            513,
            203,
            716,
            502,
            109,
            680,
            219,
            737,
            0,
            144,
            145,
            750,
            859,
            535,
            299,
            145,
            645,
            538,
            178,
            483,
            729,
            298,
            306,
            677,
            703,
            173,
            529,
            538,
            412,
            419,
            464,
            533,
            602,
            540
        ],
        [
            657,
            634,
            348,
            596,
            628,
            239,
            554,
            432,
            451,
            468,
            280,
            446,
            75,
            413,
            565,
            504,
            393,
            197,
            574,
            367,
            125,
            538,
            217,
            608,
            144,
            0,
            286,
            609,
            721,
            415,
            393,
            278,
            544,
            515,
            306,
            349,
            649,
            158,
            258,
            540,
            561,
            317,
            438,
            549,
            313,
            306,
            453,
            462,
            463,
            416
        ],
        [
            894,
            915,
            76,
            817,
            885,
            524,
            840,
            449,
            596,
            466,
            292,
            505,
            268,
            328,
            845,
            679,
            657,
            259,
            860,
            648,
            202,
            824,
            331,
            848,
            145,
            286,
            0,
            877,
            982,
            678,
            212,
            36,
            781,
            554,
            156,
            605,
            855,
            443,
            370,
            801,
            847,
            68,
            609,
            519,
            551,
            561,
            554,
            595,
            747,
            685
        ],
        [
            687,
            118,
            921,
            714,
            76,
            432,
            279,
            950,
            815,
            991,
            850,
            626,
            609,
            809,
            110,
            388,
            500,
            651,
            274,
            401,
            676,
            286,
            753,
            155,
            750,
            609,
            877,
            0,
            118,
            504,
            887,
            858,
            638,
            670,
            915,
            274,
            787,
            490,
            573,
            85,
            289,
            921,
            408,
            793,
            591,
            540,
            880,
            489,
            351,
            476
        ],
        [
            782,
            187,
            1022,
            818,
            101,
            550,
            374,
            1068,
            932,
            1110,
            967,
            687,
            715,
            888,
            214,
            431,
            614,
            747,
            364,
            517,
            780,
            384,
            870,
            172,
            859,
            721,
            982,
            118,
            0,
            616,
            977,
            961,
            743,
            722,
            1027,
            377,
            890,
            607,
            660,
            182,
            382,
            1029,
            467,
            850,
            708,
            658,
            997,
            542,
            459,
            588
        ],
        [
            259,
            446,
            750,
            236,
            567,
            211,
            269,
            520,
            328,
            559,
            492,
            768,
            476,
            813,
            401,
            678,
            22,
            592,
            288,
            116,
            540,
            253,
            393,
            606,
            535,
            415,
            678,
            504,
            616,
            0,
            808,
            680,
            161,
            836,
            626,
            420,
            308,
            271,
            601,
            490,
            267,
            686,
            640,
            911,
            145,
            118,
            407,
            707,
            161,
            27
        ],
        [
            1047,
            950,
            157,
            980,
            876,
            620,
            917,
            659,
            787,
            678,
            498,
            373,
            336,
            143,
            882,
            605,
            786,
            242,
            935,
            751,
            268,
            903,
            517,
            822,
            299,
            393,
            212,
            887,
            977,
            808,
            0,
            181,
            934,
            402,
            368,
            617,
            1027,
            544,
            317,
            804,
            926,
            271,
            541,
            333,
            701,
            698,
            755,
            500,
            841,
            808
        ],
        [
            902,
            899,
            70,
            827,
            863,
            517,
            832,
            477,
            615,
            497,
            317,
            470,
            251,
            292,
            830,
            648,
            659,
            229,
            851,
            644,
            181,
            816,
            347,
            824,
            145,
            278,
            36,
            858,
            961,
            680,
            181,
            0,
            789,
            519,
            189,
            584,
            869,
            436,
            339,
            780,
            839,
            104,
            579,
            483,
            557,
            564,
            577,
            562,
            742,
            685
        ],
        [
            113,
            561,
            856,
            77,
            707,
            367,
            372,
            525,
            292,
            558,
            548,
            925,
            612,
            954,
            530,
            839,
            179,
            732,
            386,
            275,
            669,
            360,
            464,
            754,
            645,
            544,
            781,
            638,
            743,
            161,
            934,
            789,
            0,
            993,
            701,
            581,
            151,
            416,
            753,
            636,
            365,
            777,
            801,
            1063,
            232,
            240,
            383,
            868,
            287,
            182
        ],
        [
            1096,
            769,
            537,
            1060,
            628,
            626,
            818,
            927,
            964,
            959,
            760,
            69,
            442,
            260,
            713,
            291,
            816,
            337,
            830,
            736,
            434,
            810,
            725,
            550,
            538,
            515,
            554,
            670,
            722,
            836,
            402,
            519,
            993,
            0,
            693,
            465,
            1125,
            585,
            257,
            587,
            830,
            623,
            262,
            130,
            791,
            762,
            968,
            181,
            790,
            823
        ],
        [
            810,
            933,
            219,
            724,
            935,
            514,
            829,
            299,
            477,
            313,
            162,
            637,
            326,
            481,
            865,
            777,
            606,
            369,
            849,
            622,
            284,
            812,
            238,
            912,
            178,
            306,
            156,
            915,
            1027,
            626,
            368,
            189,
            701,
            693,
            0,
            655,
            753,
            438,
            478,
            846,
            834,
            102,
            707,
            669,
            485,
            508,
            421,
            707,
            725,
            638
        ],
        [
            668,
            335,
            646,
            656,
            281,
            246,
            353,
            739,
            660,
            779,
            613,
            406,
            338,
            550,
            269,
            258,
            405,
            377,
            365,
            306,
            403,
            345,
            526,
            260,
            483,
            349,
            605,
            274,
            377,
            420,
            617,
            584,
            581,
            465,
            655,
            0,
            728,
            267,
            308,
            195,
            364,
            652,
            227,
            571,
            438,
            392,
            703,
            304,
            333,
            399
        ],
        [
            133,
            706,
            932,
            73,
            857,
            503,
            516,
            524,
            287,
            548,
            591,
            1056,
            722,
            1063,
            678,
            985,
            323,
            845,
            528,
            424,
            772,
            506,
            525,
            905,
            729,
            649,
            855,
            787,
            890,
            308,
            1027,
            869,
            151,
            1125,
            753,
            728,
            0,
            541,
            877,
            787,
            509,
            840,
            945,
            1187,
            338,
            362,
            369,
            1008,
            438,
            331
        ],
        [
            525,
            496,
            506,
            478,
            523,
            81,
            398,
            472,
            406,
            513,
            359,
            515,
            208,
            542,
            429,
            489,
            249,
            321,
            418,
            209,
            276,
            382,
            264,
            522,
            298,
            158,
            443,
            490,
            607,
            271,
            544,
            436,
            416,
            585,
            438,
            267,
            541,
            0,
            337,
            433,
            405,
            468,
            433,
            647,
            207,
            178,
            440,
            483,
            305,
            266
        ],
        [
            859,
            643,
            385,
            816,
            559,
            391,
            638,
            680,
            707,
            714,
            517,
            188,
            187,
            243,
            577,
            309,
            580,
            111,
            654,
            513,
            197,
            627,
            472,
            506,
            306,
            258,
            370,
            573,
            660,
            601,
            317,
            339,
            753,
            257,
            478,
            308,
            877,
            337,
            0,
            488,
            649,
            433,
            240,
            310,
            540,
            516,
            712,
            228,
            584,
            591
        ],
        [
            698,
            185,
            841,
            713,
            90,
            384,
            304,
            901,
            785,
            943,
            791,
            542,
            533,
            723,
            145,
            311,
            483,
            569,
            304,
            379,
            599,
            306,
            697,
            118,
            677,
            540,
            801,
            85,
            182,
            490,
            804,
            780,
            636,
            587,
            846,
            195,
            787,
            433,
            488,
            0,
            315,
            847,
            325,
            709,
            558,
            507,
            843,
            407,
            350,
            463
        ],
        [
            400,
            197,
            908,
            438,
            364,
            324,
            12,
            779,
            595,
            819,
            724,
            770,
            596,
            889,
            180,
            595,
            274,
            685,
            21,
            214,
            669,
            23,
            622,
            430,
            703,
            561,
            847,
            289,
            382,
            267,
            926,
            839,
            365,
            830,
            834,
            364,
            509,
            405,
            649,
            315,
            0,
            872,
            584,
            934,
            396,
            352,
            674,
            664,
            114,
            241
        ],
        [
            888,
            952,
            117,
            806,
            933,
            548,
            866,
            402,
            570,
            415,
            258,
            573,
            314,
            394,
            883,
            741,
            666,
            322,
            887,
            667,
            254,
            850,
            316,
            901,
            173,
            317,
            68,
            921,
            1029,
            686,
            271,
            104,
            777,
            623,
            102,
            652,
            840,
            468,
            433,
            847,
            872,
            0,
            671,
            586,
            552,
            568,
            520,
            660,
            768,
            695
        ],
        [
            893,
            507,
            625,
            875,
            369,
            445,
            572,
            868,
            839,
            906,
            717,
            220,
            387,
            431,
            453,
            69,
            623,
            350,
            581,
            528,
            424,
            566,
            651,
            297,
            529,
            438,
            609,
            408,
            467,
            640,
            541,
            579,
            801,
            262,
            707,
            227,
            945,
            433,
            240,
            325,
            584,
            671,
            0,
            386,
            633,
            593,
            867,
            82,
            561,
            621
        ],
        [
            1170,
            888,
            484,
            1126,
            755,
            701,
            923,
            931,
            999,
            958,
            763,
            168,
            474,
            193,
            829,
            421,
            890,
            354,
            936,
            820,
            446,
            913,
            745,
            678,
            538,
            549,
            519,
            793,
            850,
            911,
            333,
            483,
            1063,
            130,
            669,
            571,
            1187,
            647,
            310,
            709,
            934,
            586,
            386,
            0,
            848,
            826,
            992,
            308,
            883,
            901
        ],
        [
            346,
            554,
            625,
            282,
            644,
            192,
            396,
            382,
            227,
            422,
            347,
            721,
            384,
            726,
            500,
            683,
            129,
            507,
            416,
            194,
            438,
            379,
            250,
            666,
            412,
            313,
            551,
            591,
            708,
            145,
            701,
            557,
            232,
            791,
            485,
            438,
            338,
            207,
            540,
            558,
            396,
            552,
            633,
            848,
            0,
            50,
            289,
            687,
            282,
            163
        ],
        [
            351,
            505,
            633,
            299,
            593,
            148,
            351,
            428,
            277,
            468,
            379,
            693,
            372,
            714,
            450,
            641,
            98,
            492,
            371,
            145,
            432,
            333,
            279,
            616,
            419,
            306,
            561,
            540,
            658,
            118,
            698,
            564,
            240,
            762,
            508,
            392,
            362,
            178,
            516,
            507,
            352,
            568,
            593,
            826,
            50,
            0,
            339,
            651,
            238,
            129
        ],
        [
            466,
            843,
            628,
            368,
            931,
            462,
            675,
            155,
            90,
            180,
            262,
            900,
            526,
            830,
            789,
            926,
            400,
            639,
            695,
            483,
            546,
            659,
            247,
            947,
            464,
            453,
            554,
            880,
            997,
            407,
            755,
            577,
            383,
            968,
            421,
            703,
            369,
            440,
            712,
            843,
            674,
            520,
            867,
            992,
            289,
            339,
            0,
            905,
            564,
            433
        ],
        [
            963,
            589,
            600,
            939,
            447,
            505,
            653,
            894,
            885,
            930,
            736,
            148,
            401,
            377,
            536,
            115,
            689,
            339,
            662,
            598,
            424,
            646,
            679,
            370,
            533,
            462,
            595,
            489,
            542,
            707,
            500,
            562,
            868,
            181,
            707,
            304,
            1008,
            483,
            228,
            407,
            664,
            660,
            82,
            308,
            687,
            651,
            905,
            0,
            637,
            689
        ],
        [
            350,
            285,
            811,
            365,
            419,
            224,
            113,
            665,
            488,
            705,
            611,
            726,
            506,
            818,
            244,
            585,
            163,
            605,
            133,
            102,
            578,
            96,
            509,
            468,
            602,
            463,
            747,
            351,
            459,
            161,
            841,
            742,
            287,
            790,
            725,
            333,
            438,
            305,
            584,
            350,
            114,
            768,
            561,
            883,
            282,
            238,
            564,
            637,
            0,
            133
        ],
        [
            273,
            418,
            755,
            258,
            540,
            200,
            242,
            542,
            355,
            582,
            508,
            755,
            474,
            808,
            374,
            657,
            34,
            588,
            261,
            93,
            540,
            226,
            408,
            580,
            540,
            416,
            685,
            476,
            588,
            27,
            808,
            685,
            182,
            823,
            638,
            399,
            331,
            266,
            591,
            463,
            241,
            695,
            621,
            901,
            163,
            129,
            433,
            689,
            133,
            0
        ]
    ]
}