{
    "config": {
        "max_coordinate": 1000
    },
    "nodes": 50,
    "node_positions": [
        [
            139,
            130
        ],
        [
            415,
            37
        ],
        [
            959,
            656
        ],
        [
            606,
            999
        ],
        [
            105,
            296
        ],
        [
            478,
            148
        ],
        [
            533,
            627
        ],
        [
            888,
            233
        ],
        [
            262,
            606
        ],
        [
            880,
            109
        ],
        [
            663,
            108
        ],
        [
            566,
            413
        ],
        [
            957,
            252
        ],
        [
            437,
            863
        ],
        [
            920,
            590
        ],
        [
            592,
            566
        ],
        [
            199,
            656
        ],
        [
            951,
            367
        ],
        [
            284,
            346
        ],
        [
            79,
            935
        ],
        [
            851,
            411
        ],
        [
            110,
            907
        ],
        [
            977,
            523
        ],
        [
            968,
            609
        ],
        [
            692,
            936
        ],
        [
            212,
            924
        ],
        [
            614,
            556
        ],
        [
            302,
            439
        ],
        [
            752,
            682
        ],
        [
            683,
            399
        ],
        [
            238,
            241
        ],
        [
            35,
            309
        ],
        [
            687,
            908
        ],
        [
            268,
            916
        ],
        [
            298,
            231
        ],
        [
            728,
            342
        ],
        [
            619,
            490
        ],
        [
            220,
            540
        ],
        [
            41,
            309
        ],
        [
            214,
            554
        ],
        [
            913,
            235
        ],
        [
            525,
            706
        ],
        [
            562,
            874
        ],
        [
            975,
            738
        ],
        [
            577,
            597
        ],
        [
            861,
            752
        ],
        [
            265,
            770
        ],
        [
            563,
            406
        ],
        [
            234,
            81
        ],
        [
            986,
            94
        ]
    ],
    "dist": [
        [
            0,
            291,
            974,
            986,
            169,
            339,
            634,
            756,
            491,
            741,
            524,
            512,
            827,
            791,
            906,
            628,
            529,
            845,
            260,
            807,
            765,
            777,
            925,
            957,
            977,
            797,
            638,
            349,
            824,
            606,
            148,
            207,
            951,
            796,
            188,
            625,
            600,
            417,
            204,
            430,
            781,
            693,
            855,
            1033,
            640,
            952,
            652,
            505,
            106,
            847
        ],
        [
            291,
            0,
            824,
            980,
            403,
            127,
            601,
            512,
            589,
            470,
            257,
            405,
            583,
            826,
            748,
            557,
            655,
            629,
            335,
            958,
            574,
            921,
            742,
            795,
            940,
            909,
            555,
            417,
            727,
            450,
            270,
            467,
            912,
            891,
            226,
            437,
            496,
            539,
            462,
            554,
            535,
            677,
            849,
            897,
            582,
            842,
            748,
            397,
            186,
            573
        ],
        [
            974,
            824,
            0,
            492,
            926,
            699,
            426,
            428,
            698,
            552,
            622,
            462,
            404,
            561,
            76,
            377,
            760,
            289,
            742,
            923,
            267,
            885,
            134,
            47,
            386,
            793,
            359,
            691,
            208,
            377,
            831,
            987,
            370,
            738,
            785,
            389,
            378,
            748,
            981,
            751,
            423,
            436,
            452,
            83,
            386,
            137,
            703,
            468,
            925,
            562
        ],
        [
            986,
            980,
            492,
            0,
            863,
            860,
            379,
            816,
            522,
            931,
            892,
            587,
            825,
            216,
            515,
            433,
            532,
            720,
            728,
            530,
            637,
            504,
            603,
            532,
            106,
            401,
            443,
            637,
            349,
            604,
            842,
            895,
            121,
            348,
            827,
            668,
            509,
            599,
            891,
            593,
            823,
            303,
            132,
            451,
            403,
            355,
            410,
            594,
            990,
            981
        ],
        [
            169,
            403,
            926,
            863,
            0,
            401,
            541,
            785,
            347,
            797,
            588,
            475,
            853,
            657,
            866,
            556,
            372,
            848,
            185,
            639,
            754,
            611,
            901,
            918,
            868,
            637,
            571,
            243,
            753,
            587,
            143,
            71,
            844,
            641,
            203,
            624,
            549,
            269,
            65,
            280,
            810,
            586,
            736,
            975,
            559,
            882,
            500,
            471,
            250,
            903
        ],
        [
            339,
            127,
            699,
            860,
            401,
            0,
            482,
            418,
            506,
            403,
            189,
            279,
            490,
            716,
            625,
            433,
            579,
            521,
            277,
            882,
            456,
            843,
            624,
            672,
            816,
            820,
            430,
            340,
            600,
            324,
            257,
            471,
            788,
            796,
            198,
            316,
            369,
            469,
            465,
            484,
            443,
            559,
            730,
            771,
            459,
            715,
            657,
            271,
            253,
            510
        ],
        [
            634,
            601,
            426,
            379,
            541,
            482,
            0,
            530,
            271,
            623,
            535,
            216,
            566,
            254,
            388,
            84,
            335,
            492,
            375,
            548,
            384,
            507,
            456,
            435,
            347,
            437,
            107,
            297,
            225,
            272,
            485,
            590,
            320,
            392,
            460,
            345,
            161,
            324,
            585,
            327,
            545,
            79,
            248,
            455,
            53,
            351,
            303,
            223,
            622,
            699
        ],
        [
            756,
            512,
            428,
            816,
            785,
            418,
            530,
            0,
            728,
            124,
            257,
            368,
            71,
            774,
            358,
            445,
            808,
            148,
            614,
            1071,
            181,
            1029,
            303,
            384,
            729,
            966,
            423,
            621,
            469,
            263,
            650,
            856,
            704,
            922,
            590,
            193,
            372,
            735,
            850,
            746,
            25,
            596,
            719,
            512,
            478,
            519,
            822,
            368,
            671,
            170
        ],
        [
            491,
            589,
            698,
            522,
            347,
            506,
            271,
            728,
            0,
            793,
            639,
            360,
            779,
            310,
            658,
            332,
            80,
            729,
            260,
            376,
            620,
            337,
            719,
            706,
            542,
            321,
            355,
            171,
            495,
            469,
            365,
            373,
            521,
            310,
            376,
            535,
            375,
            78,
            370,
            70,
            749,
            281,
            402,
            725,
            315,
            616,
            164,
            361,
            525,
            886
        ],
        [
            741,
            470,
            552,
            931,
            797,
            403,
            623,
            124,
            793,
            0,
            217,
            437,
            162,
            874,
            482,
            540,
            873,
            267,
            641,
            1150,
            303,
            1108,
            425,
            507,
            848,
            1053,
            520,
            665,
            587,
            350,
            655,
            868,
            821,
            1012,
            594,
            278,
            461,
            788,
            862,
            800,
            130,
            694,
            828,
            636,
            574,
            643,
            902,
            434,
            646,
            107
        ],
        [
            524,
            257,
            622,
            892,
            588,
            189,
            535,
            257,
            639,
            217,
            0,
            320,
            327,
            788,
            546,
            463,
            718,
            387,
            447,
            1012,
            356,
            971,
            520,
            586,
            828,
            932,
            450,
            489,
            580,
            291,
            445,
            659,
            800,
            899,
            385,
            242,
            384,
            618,
            653,
            632,
            280,
            613,
            772,
            703,
            496,
            673,
            772,
            314,
            429,
            323
        ],
        [
            512,
            405,
            462,
            587,
            475,
            279,
            216,
            368,
            360,
            437,
            320,
            0,
            422,
            468,
            395,
            155,
            440,
            387,
            289,
            713,
            285,
            672,
            425,
            447,
            537,
            621,
            150,
            265,
            327,
            117,
            370,
            541,
            509,
            584,
            323,
            176,
            93,
            368,
            535,
            379,
            389,
            295,
            461,
            522,
            184,
            449,
            466,
            7,
            469,
            527
        ],
        [
            827,
            583,
            404,
            825,
            853,
            490,
            566,
            71,
            779,
            162,
            327,
            422,
            0,
            802,
            340,
            481,
            858,
            115,
            679,
            1112,
            191,
            1070,
            271,
            357,
            733,
            1003,
            458,
            681,
            476,
            310,
            719,
            923,
            709,
            956,
            659,
            246,
            413,
            791,
            917,
            802,
            47,
            626,
            736,
            486,
            513,
            509,
            864,
            423,
            742,
            160
        ],
        [
            791,
            826,
            561,
            216,
            657,
            716,
            254,
            774,
            310,
            874,
            788,
            468,
            802,
            0,
            554,
            335,
            315,
            714,
            539,
            365,
            612,
            329,
            638,
            588,
            265,
            233,
            354,
            444,
            363,
            525,
            653,
            684,
            254,
            177,
            647,
            596,
            415,
            389,
            680,
            381,
            788,
            179,
            125,
            552,
            300,
            438,
            195,
            474,
            807,
            944
        ],
        [
            906,
            748,
            76,
            515,
            866,
            625,
            388,
            358,
            658,
            482,
            546,
            395,
            340,
            554,
            0,
            328,
            724,
            225,
            681,
            909,
            191,
            869,
            87,
            51,
            414,
            782,
            307,
            636,
            191,
            304,
            766,
            928,
            394,
            728,
            718,
            313,
            317,
            701,
            922,
            706,
            355,
            411,
            456,
            157,
            343,
            172,
            679,
            401,
            854,
            500
        ],
        [
            628,
            557,
            377,
            433,
            556,
            433,
            84,
            445,
            332,
            540,
            463,
            155,
            481,
            335,
            328,
            0,
            403,
            410,
            378,
            631,
            301,
            590,
            387,
            378,
            383,
            522,
            24,
            316,
            197,
            190,
            480,
            613,
            354,
            476,
            445,
            262,
            80,
            372,
            607,
            378,
            461,
            155,
            309,
            419,
            34,
            327,
            385,
            162,
            602,
            614
        ],
        [
            529,
            655,
            760,
            532,
            372,
            579,
            335,
            808,
            80,
            873,
            718,
            440,
            858,
            315,
            724,
            403,
            0,
            805,
            321,
            303,
            696,
            266,
            789,
            770,
            566,
            268,
            426,
            240,
            553,
            548,
            416,
            383,
            549,
            269,
            436,
            615,
            451,
            117,
            381,
            103,
            828,
            329,
            423,
            780,
            382,
            668,
            131,
            441,
            576,
            967
        ],
        [
            845,
            629,
            289,
            720,
            848,
            521,
            492,
            148,
            729,
            267,
            387,
            387,
            115,
            714,
            225,
            410,
            805,
            0,
            667,
            1040,
            109,
            999,
            158,
            242,
            625,
            925,
            386,
            652,
            372,
            269,
            724,
            917,
            601,
            876,
            667,
            224,
            354,
            751,
            911,
            760,
            137,
            544,
            639,
            371,
            439,
            395,
            795,
            389,
            771,
            275
        ],
        [
            260,
            335,
            742,
            728,
            185,
            277,
            375,
            614,
            260,
            641,
            447,
            289,
            679,
            539,
            681,
            378,
            321,
            667,
            0,
            623,
            570,
            587,
            715,
            732,
            717,
            582,
            391,
            94,
            576,
            402,
            114,
            251,
            691,
            570,
            115,
            444,
            364,
            204,
            245,
            219,
            638,
            433,
            596,
            794,
            385,
            705,
            424,
            285,
            269,
            745
        ],
        [
            807,
            958,
            923,
            530,
            639,
            882,
            548,
            1071,
            376,
            1150,
            1012,
            713,
            1112,
            365,
            909,
            631,
            303,
            1040,
            623,
            0,
            933,
            41,
            988,
            946,
            613,
            133,
            655,
            543,
            718,
            807,
            711,
            627,
            608,
            189,
            737,
            879,
            699,
            419,
            627,
            404,
            1088,
            501,
            486,
            917,
            601,
            803,
            248,
            717,
            867,
            1236
        ],
        [
            765,
            574,
            267,
            637,
            754,
            456,
            384,
            181,
            620,
            303,
            356,
            285,
            191,
            612,
            191,
            301,
            696,
            109,
            570,
            933,
            0,
            891,
            168,
            229,
            548,
            819,
            277,
            549,
            288,
            168,
            636,
            822,
            523,
            771,
            581,
            141,
            245,
            644,
            816,
            652,
            186,
            439,
            545,
            349,
            331,
            341,
            687,
            288,
            699,
            344
        ],
        [
            777,
            921,
            885,
            504,
            611,
            843,
            507,
            1029,
            337,
            1108,
            971,
            672,
            1070,
            329,
            869,
            590,
            266,
            999,
            587,
            41,
            891,
            0,
            948,
            908,
            582,
            103,
            614,
            505,
            680,
            765,
            678,
            602,
            577,
            158,
            701,
            837,
            658,
            383,
            601,
            368,
            1047,
            461,
            453,
            881,
            560,
            766,
            206,
            675,
            835,
            1195
        ],
        [
            925,
            742,
            134,
            603,
            901,
            624,
            456,
            303,
            719,
            425,
            520,
            425,
            271,
            638,
            87,
            387,
            789,
            158,
            715,
            988,
            168,
            948,
            0,
            86,
            501,
            863,
            364,
            680,
            275,
            319,
            790,
            966,
            482,
            810,
            739,
            307,
            359,
            757,
            960,
            763,
            295,
            487,
            543,
            215,
            406,
            256,
            753,
            430,
            864,
            429
        ],
        [
            957,
            795,
            47,
            532,
            918,
            672,
            435,
            384,
            706,
            507,
            586,
            447,
            357,
            588,
            51,
            378,
            770,
            242,
            732,
            946,
            229,
            908,
            86,
            0,
            427,
            819,
            357,
            687,
            228,
            354,
            817,
            980,
            410,
            764,
            769,
            359,
            368,
            751,
            974,
            756,
            378,
            453,
            484,
            129,
            391,
            178,
            721,
            453,
            904,
            515
        ],
        [
            977,
            940,
            386,
            106,
            868,
            816,
            347,
            729,
            542,
            848,
            828,
            537,
            733,
            265,
            414,
            383,
            566,
            625,
            717,
            613,
            548,
            582,
            501,
            427,
            0,
            480,
            387,
            631,
            260,
            537,
            830,
            908,
            28,
            424,
            807,
            595,
            451,
            616,
            903,
            611,
            735,
            284,
            144,
            345,
            357,
            249,
            458,
            545,
            969,
            891
        ],
        [
            797,
            909,
            793,
            401,
            637,
            820,
            437,
            966,
            321,
            1053,
            932,
            621,
            1003,
            233,
            782,
            522,
            268,
            925,
            582,
            133,
            819,
            103,
            863,
            819,
            480,
            0,
            545,
            493,
            591,
            705,
            683,
            639,
            475,
            56,
            698,
            777,
            594,
            384,
            638,
            370,
            982,
            381,
            353,
            785,
            490,
            671,
            162,
            625,
            843,
            1134
        ],
        [
            638,
            555,
            359,
            443,
            571,
            430,
            107,
            423,
            355,
            520,
            450,
            150,
            458,
            354,
            307,
            24,
            426,
            386,
            391,
            655,
            277,
            614,
            364,
            357,
            387,
            545,
            0,
            333,
            186,
            171,
            490,
            629,
            359,
            499,
            453,
            242,
            66,
            394,
            623,
            400,
            438,
            174,
            322,
            404,
            55,
            315,
            409,
            158,
            608,
            593
        ],
        [
            349,
            417,
            691,
            637,
            243,
            340,
            297,
            621,
            171,
            665,
            489,
            265,
            681,
            444,
            636,
            316,
            240,
            652,
            94,
            543,
            549,
            505,
            680,
            687,
            631,
            493,
            333,
            0,
            511,
            383,
            208,
            296,
            606,
            478,
            208,
            436,
            321,
            130,
            291,
            144,
            644,
            347,
            506,
            736,
            317,
            640,
            333,
            263,
            364,
            766
        ],
        [
            824,
            727,
            208,
            349,
            753,
            600,
            225,
            469,
            495,
            587,
            580,
            327,
            476,
            363,
            191,
            197,
            553,
            372,
            576,
            718,
            288,
            680,
            275,
            228,
            260,
            591,
            186,
            511,
            0,
            291,
            677,
            808,
            235,
            537,
            639,
            340,
            233,
            550,
            802,
            553,
            475,
            228,
            270,
            229,
            194,
            129,
            494,
            334,
            793,
            632
        ],
        [
            606,
            450,
            377,
            604,
            587,
            324,
            272,
            263,
            469,
            350,
            291,
            117,
            310,
            525,
            304,
            190,
            548,
            269,
            402,
            807,
            168,
            765,
            319,
            354,
            537,
            705,
            171,
            383,
            291,
            0,
            472,
            654,
            509,
            662,
            420,
            72,
            111,
            483,
            648,
            493,
            282,
            345,
            490,
            447,
            224,
            395,
            558,
            120,
            550,
            429
        ],
        [
            148,
            270,
            831,
            842,
            143,
            257,
            485,
            650,
            365,
            655,
            445,
            370,
            719,
            653,
            766,
            480,
            416,
            724,
            114,
            711,
            636,
            678,
            790,
            817,
            830,
            683,
            490,
            208,
            677,
            472,
            0,
            214,
            804,
            675,
            60,
            500,
            455,
            299,
            208,
            313,
            675,
            546,
            711,
            888,
            491,
            805,
            529,
            364,
            160,
            762
        ],
        [
            207,
            467,
            987,
            895,
            71,
            471,
            590,
            856,
            373,
            868,
            659,
            541,
            923,
            684,
            928,
            613,
            383,
            917,
            251,
            627,
            822,
            602,
            966,
            980,
            908,
            639,
            629,
            296,
            808,
            654,
            214,
            0,
            885,
            650,
            274,
            693,
            611,
            295,
            6,
            303,
            881,
            630,
            772,
            1033,
            613,
            937,
            515,
            536,
            302,
            975
        ],
        [
            951,
            912,
            370,
            121,
            844,
            788,
            320,
            704,
            521,
            821,
            800,
            509,
            709,
            254,
            394,
            354,
            549,
            601,
            691,
            608,
            523,
            577,
            482,
            410,
            28,
            475,
            359,
            606,
            235,
            509,
            804,
            885,
            0,
            419,
            780,
            567,
            423,
            594,
            880,
            590,
            709,
            258,
            129,
            334,
            329,
            233,
            443,
            517,
            942,
            867
        ],
        [
            796,
            891,
            738,
            348,
            641,
            796,
            392,
            922,
            310,
            1012,
            899,
            584,
            956,
            177,
            728,
            476,
            269,
            876,
            570,
            189,
            771,
            158,
            810,
            764,
            424,
            56,
            499,
            478,
            537,
            662,
            675,
            650,
            419,
            0,
            685,
            735,
            551,
            379,
            648,
            366,
            937,
            331,
            296,
            729,
            444,
            615,
            146,
            589,
            835,
            1091
        ],
        [
            188,
            226,
            785,
            827,
            203,
            198,
            460,
            590,
            376,
            594,
            385,
            323,
            659,
            647,
            718,
            445,
            436,
            667,
            115,
            737,
            581,
            701,
            739,
            769,
            807,
            698,
            453,
            208,
            639,
            420,
            60,
            274,
            780,
            685,
            0,
            444,
            412,
            318,
            268,
            333,
            615,
            526,
            695,
            845,
            460,
            767,
            540,
            317,
            163,
            701
        ],
        [
            625,
            437,
            389,
            668,
            624,
            316,
            345,
            193,
            535,
            278,
            242,
            176,
            246,
            596,
            313,
            262,
            615,
            224,
            444,
            879,
            141,
            837,
            307,
            359,
            595,
            777,
            242,
            436,
            340,
            72,
            500,
            693,
            567,
            735,
            444,
            0,
            183,
            545,
            687,
            556,
            213,
            416,
            557,
            466,
            296,
            431,
            630,
            176,
            558,
            357
        ],
        [
            600,
            496,
            378,
            509,
            549,
            369,
            161,
            372,
            375,
            461,
            384,
            93,
            413,
            415,
            317,
            80,
            451,
            354,
            364,
            699,
            245,
            658,
            359,
            368,
            451,
            594,
            66,
            321,
            233,
            111,
            455,
            611,
            423,
            551,
            412,
            183,
            0,
            402,
            605,
            410,
            389,
            235,
            388,
            433,
            114,
            356,
            451,
            100,
            561,
            539
        ],
        [
            417,
            539,
            748,
            599,
            269,
            469,
            324,
            735,
            78,
            788,
            618,
            368,
            791,
            389,
            701,
            372,
            117,
            751,
            204,
            419,
            644,
            383,
            757,
            751,
            616,
            384,
            394,
            130,
            550,
            483,
            299,
            295,
            594,
            379,
            318,
            545,
            402,
            0,
            292,
            15,
            757,
            347,
            478,
            780,
            361,
            675,
            234,
            368,
            459,
            886
        ],
        [
            204,
            462,
            981,
            891,
            65,
            465,
            585,
            850,
            370,
            862,
            653,
            535,
            917,
            680,
            922,
            607,
            381,
            911,
            245,
            627,
            816,
            601,
            960,
            974,
            903,
            638,
            623,
            291,
            802,
            648,
            208,
            6,
            880,
            648,
            268,
            687,
            605,
            292,
            0,
            299,
            875,
            625,
            768,
            1027,
            608,
            932,
            512,
            530,
            298,
            969
        ],
        [
            430,
            554,
            751,
            593,
            280,
            484,
            327,
            746,
            70,
            800,
            632,
            379,
            802,
            381,
            706,
            378,
            103,
            760,
            219,
            404,
            652,
            368,
            763,
            756,
            611,
            370,
            400,
            144,
            553,
            493,
            313,
            303,
            590,
            366,
            333,
            556,
            410,
            15,
            299,
            0,
            768,
            346,
            472,
            782,
            365,
            676,
            221,
            379,
            473,
            898
        ],
        [
            781,
            535,
            423,
            823,
            810,
            443,
            545,
            25,
            749,
            130,
            280,
            389,
            47,
            788,
            355,
            461,
            828,
            137,
            638,
            1088,
            186,
            1047,
            295,
            378,
            735,
            982,
            438,
            644,
            475,
            282,
            675,
            881,
            709,
            937,
            615,
            213,
            389,
            757,
            875,
            768,
            0,
            610,
            729,
            506,
            493,
            519,
            840,
            389,
            696,
            158
        ],
        [
            693,
            677,
            436,
            303,
            586,
            559,
            79,
            596,
            281,
            694,
            613,
            295,
            626,
            179,
            411,
            155,
            329,
            544,
            433,
            501,
            439,
            461,
            487,
            453,
            284,
            381,
            174,
            347,
            228,
            345,
            546,
            630,
            258,
            331,
            526,
            416,
            235,
            347,
            625,
            346,
            610,
            0,
            172,
            451,
            120,
            339,
            267,
            302,
            689,
            766
        ],
        [
            855,
            849,
            452,
            132,
            736,
            730,
            248,
            719,
            402,
            828,
            772,
            461,
            736,
            125,
            456,
            309,
            423,
            639,
            596,
            486,
            545,
            453,
            543,
            484,
            144,
            353,
            322,
            506,
            270,
            490,
            711,
            772,
            129,
            296,
            695,
            557,
            388,
            478,
            768,
            472,
            729,
            172,
            0,
            434,
            277,
            322,
            314,
            468,
            858,
            887
        ],
        [
            1033,
            897,
            83,
            451,
            975,
            771,
            455,
            512,
            725,
            636,
            703,
            522,
            486,
            552,
            157,
            419,
            780,
            371,
            794,
            917,
            349,
            881,
            215,
            129,
            345,
            785,
            404,
            736,
            229,
            447,
            888,
            1033,
            334,
            729,
            845,
            466,
            433,
            780,
            1027,
            782,
            506,
            451,
            434,
            0,
            422,
            114,
            710,
            529,
            990,
            644
        ],
        [
            640,
            582,
            386,
            403,
            559,
            459,
            53,
            478,
            315,
            574,
            496,
            184,
            513,
            300,
            343,
            34,
            382,
            439,
            385,
            601,
            331,
            560,
            406,
            391,
            357,
            490,
            55,
            317,
            194,
            224,
            491,
            613,
            329,
            444,
            460,
            296,
            114,
            361,
            608,
            365,
            493,
            120,
            277,
            422,
            0,
            323,
            356,
            191,
            619,
            648
        ],
        [
            952,
            842,
            137,
            355,
            882,
            715,
            351,
            519,
            616,
            643,
            673,
            449,
            509,
            438,
            172,
            327,
            668,
            395,
            705,
            803,
            341,
            766,
            256,
            178,
            249,
            671,
            315,
            640,
            129,
            395,
            805,
            937,
            233,
            615,
            767,
            431,
            356,
            675,
            932,
            676,
            519,
            339,
            322,
            114,
            323,
            0,
            596,
            456,
            918,
            669
        ],
        [
            652,
            748,
            703,
            410,
            500,
            657,
            303,
            822,
            164,
            902,
            772,
            466,
            864,
            195,
            679,
            385,
            131,
            795,
            424,
            248,
            687,
            206,
            753,
            721,
            458,
            162,
            409,
            333,
            494,
            558,
            529,
            515,
            443,
            146,
            540,
            630,
            451,
            234,
            512,
            221,
            840,
            267,
            314,
            710,
            356,
            596,
            0,
            470,
            689,
            988
        ],
        [
            505,
            397,
            468,
            594,
            471,
            271,
            223,
            368,
            361,
            434,
            314,
            7,
            423,
            474,
            401,
            162,
            441,
            389,
            285,
            717,
            288,
            675,
            430,
            453,
            545,
            625,
            158,
            263,
            334,
            120,
            364,
            536,
            517,
            589,
            317,
            176,
            100,
            368,
            530,
            379,
            389,
            302,
            468,
            529,
            191,
            456,
            470,
            0,
            462,
            525
        ],
        [
            106,
            186,
            925,
            990,
            250,
            253,
            622,
            671,
            525,
            646,
            429,
            469,
            742,
            807,
            854,
            602,
            576,
            771,
            269,
            867,
            699,
            835,
            864,
            904,
            969,
            843,
            608,
            364,
            793,
            550,
            160,
            302,
            942,
            835,
            163,
            558,
            561,
            459,
            298,
            473,
            696,
            689,
            858,
            990,
            619,
            918,
            689,
            462,
            0,
            752
        ],
        [
            847,
            573,
            562,
            981,
            903,
            510,
            699,
            170,
            886,
            107,
            323,
            527,
            160,
            944,
            500,
            614,
            967,
            275,
            745,
            1236,
            344,
            1195,
            429,
            515,
            891,
            1134,
            593,
            766,
            632,
            429,
            762,
            975,
            867,
            1091,
            701,
            357,
            539,
            886,
            969,
            898,
            158,
            766,
            887,
            644,
            648,
            669,
            988,
            525,
            752,
            0
        ]
    ]
}