{
    "config": {
        "max_coordinate": 1000
    },
    "nodes": 50,
    "node_positions": [
        [
            114,
            143
        ],
        [
            417,
            913
        ],
        [
            844,
            913
        ],
        [
            843,
            838
        ],
        [
            605,
            286
        ],
        [
            590,
            237
        ],
        [
            587,
            18
        ],
        [
            763,
            195
        ],
        [
            230,
            40
        ],
        [
            165,
            841
        ],
        [
            919,
            589
        ],
        [
            805,
            146
        ],
        [
            463,
            568
        ],
        [
            976,
            705
        ],
        [
            310,
            14
        ],
        [
            39,
            246
        ],
        [
            76,
            930
        ],
        [
            938,
            739
        ],
        [
            370,
            910
        ],
        [
            960,
            80
        ],
        [
            378,
            896
        ],
        [
            886,
            658
        ],
        [
            187,
            175
        ],
        [
            976,
            689
        ],
        [
            639,
            955
        ],
        [
            210,
            936
        ],
        [
            759,
            910
        ],
        [
            87,
            54
        ],
        [
            142,
            829
        ],
        [
            119,
            537
        ],
        [
            113,
            27
        ],
        [
            706,
            654
        ],
        [
            976,
            969
        ],
        [
            828,
            506
        ],
        [
            862,
            959
        ],
        [
            574,
            870
        ],
        [
            164,
            44
        ],
        [
            194,
            393
        ],
        [
            147,
            458
        ],
        [
            98,
            358
        ],
        [
            568,
            537
        ],
        [
            842,
            602
        ],
        [
            356,
            833
        ],
        [
            130,
            616
        ],
        [
            424,
            266
        ],
        [
            279,
            275
        ],
        [
            362,
            596
        ],
        [
            107,
            272
        ],
        [
            863,
            911
        ],
        [
            162,
            519
        ]
    ],
    "dist": [
        [
            0,
            827,
            1061,
            1007,
            511,
            485,
            489,
            651,
            155,
            699,
            920,
            691,
            549,
            1029,
            234,
            127,
            787,
            1016,
            808,
            848,
            797,
            928,
            79,
            1020,
            966,
            798,
            1002,
            93,
            686,
            394,
            116,
            782,
            1193,
            800,
            1106,
            860,
            110,
            262,
            316,
            215,
            601,
            860,
            731,
            473,
            333,
            211,
            516,
            129,
            1072,
            379
        ],
        [
            827,
            0,
            427,
            432,
            654,
            697,
            911,
            797,
            892,
            262,
            597,
            859,
            348,
            596,
            905,
            766,
            341,
            549,
            47,
            994,
            42,
            533,
            773,
            602,
            225,
            208,
            342,
            920,
            287,
            479,
            936,
            388,
            561,
            578,
            447,
            162,
            905,
            565,
            529,
            640,
            405,
            526,
            100,
            413,
            647,
            652,
            321,
            712,
            446,
            469
        ],
        [
            1061,
            427,
            0,
            75,
            671,
            722,
            931,
            722,
            1067,
            682,
            332,
            767,
            513,
            246,
            1045,
            1045,
            768,
            197,
            474,
            841,
            466,
            258,
            988,
            260,
            209,
            634,
            85,
            1144,
            707,
            816,
            1148,
            293,
            143,
            407,
            49,
            273,
            1103,
            832,
            832,
            929,
            466,
            311,
            494,
            773,
            771,
            852,
            576,
            976,
            19,
            787
        ],
        [
            1007,
            432,
            75,
            0,
            601,
            652,
            859,
            647,
            1006,
            678,
            260,
            693,
            466,
            188,
            981,
            998,
            772,
            137,
            478,
            766,
            468,
            185,
            932,
            199,
            235,
            640,
            110,
            1089,
            701,
            784,
            1091,
            229,
            186,
            332,
            122,
            270,
            1044,
            786,
            792,
            886,
            407,
            236,
            487,
            746,
            709,
            796,
            538,
            928,
            75,
            752
        ],
        [
            511,
            654,
            671,
            601,
            0,
            51,
            268,
            182,
            448,
            708,
            436,
            244,
            315,
            559,
            401,
            567,
            833,
            562,
            666,
            410,
            650,
            466,
            432,
            547,
            669,
            760,
            642,
            567,
            713,
            546,
            556,
            381,
            777,
            313,
            720,
            584,
            503,
            424,
            489,
            512,
            253,
            395,
            601,
            578,
            182,
            326,
            393,
            498,
            676,
            500
        ],
        [
            485,
            697,
            722,
            652,
            51,
            0,
            219,
            178,
            410,
            738,
            481,
            233,
            354,
            606,
            357,
            551,
            862,
            610,
            708,
            401,
            692,
            514,
            407,
            594,
            719,
            795,
            693,
            535,
            742,
            558,
            521,
            432,
            827,
            359,
            771,
            633,
            467,
            425,
            495,
            506,
            300,
            443,
            640,
            596,
            168,
            313,
            425,
            484,
            727,
            512
        ],
        [
            489,
            911,
            931,
            859,
            268,
            219,
            0,
            249,
            357,
            924,
            660,
            252,
            563,
            789,
            277,
            593,
            1045,
            801,
            918,
            378,
            902,
            706,
            429,
            775,
            938,
            992,
            908,
            501,
            925,
            698,
            474,
            647,
            1027,
            544,
            980,
            852,
            423,
            543,
            622,
            595,
            519,
            637,
            847,
            752,
            296,
            401,
            620,
            543,
            934,
            656
        ],
        [
            651,
            797,
            722,
            647,
            182,
            178,
            249,
            0,
            555,
            880,
            423,
            64,
            478,
            552,
            487,
            725,
            1006,
            571,
            815,
            228,
            799,
            479,
            576,
            537,
            770,
            924,
            715,
            690,
            887,
            729,
            671,
            462,
            802,
            317,
            770,
            700,
            617,
            602,
            669,
            684,
            393,
            414,
            756,
            760,
            346,
            490,
            567,
            660,
            722,
            682
        ],
        [
            155,
            892,
            1067,
            1006,
            448,
            410,
            357,
            555,
            0,
            803,
            880,
            584,
            577,
            999,
            84,
            280,
            903,
            994,
            881,
            731,
            868,
            901,
            141,
            988,
            1002,
            896,
            1018,
            143,
            793,
            509,
            117,
            776,
            1191,
            758,
            1115,
            898,
            66,
            354,
            426,
            344,
            601,
            830,
            802,
            584,
            297,
            240,
            571,
            262,
            1076,
            483
        ],
        [
            699,
            262,
            682,
            678,
            708,
            738,
            924,
            880,
            803,
            0,
            794,
            944,
            404,
            822,
            839,
            608,
            125,
            779,
            216,
            1100,
            219,
            743,
            666,
            825,
            487,
            105,
            597,
            790,
            25,
            307,
            815,
            572,
            821,
            742,
            706,
            410,
            797,
            448,
            383,
            487,
            504,
            717,
            191,
            227,
            630,
            577,
            314,
            571,
            701,
            322
        ],
        [
            920,
            597,
            332,
            260,
            436,
            481,
            660,
            423,
            880,
            794,
            0,
            457,
            456,
            129,
            837,
            944,
            909,
            151,
            635,
            510,
            622,
            76,
            840,
            115,
            460,
            789,
            358,
            989,
            813,
            801,
            982,
            222,
            384,
            123,
            374,
            444,
            931,
            751,
            783,
            852,
            354,
            78,
            613,
            789,
            591,
            712,
            557,
            871,
            326,
            760
        ],
        [
            691,
            859,
            767,
            693,
            244,
            233,
            252,
            64,
            584,
            944,
            457,
            0,
            543,
            584,
            512,
            772,
            1070,
            607,
            879,
            168,
            863,
            518,
            618,
            569,
            825,
            989,
            765,
            723,
            951,
            789,
            702,
            517,
            840,
            360,
            814,
            759,
            649,
            659,
            728,
            738,
            457,
            457,
            820,
            822,
            399,
            541,
            631,
            709,
            767,
            743
        ],
        [
            549,
            348,
            513,
            466,
            315,
            354,
            563,
            478,
            577,
            404,
            456,
            543,
            0,
            530,
            574,
            532,
            529,
            504,
            354,
            696,
            338,
            432,
            480,
            527,
            425,
            446,
            452,
            636,
            413,
            345,
            644,
            257,
            651,
            370,
            558,
            321,
            603,
            320,
            334,
            421,
            109,
            380,
            285,
            336,
            304,
            345,
            104,
            462,
            526,
            304
        ],
        [
            1029,
            596,
            246,
            188,
            559,
            606,
            789,
            552,
            999,
            822,
            129,
            584,
            530,
            0,
            959,
            1043,
            927,
            50,
            639,
            625,
            627,
            101,
            950,
            16,
            419,
            800,
            298,
            1101,
            843,
            873,
            1097,
            274,
            264,
            248,
            278,
            434,
            1047,
            841,
            865,
            944,
            441,
            169,
            633,
            850,
            705,
            818,
            623,
            970,
            234,
            834
        ],
        [
            234,
            905,
            1045,
            981,
            401,
            357,
            277,
            487,
            84,
            839,
            837,
            512,
            574,
            959,
            0,
            356,
            945,
            959,
            898,
            653,
            884,
            864,
            202,
            948,
            996,
            927,
            1002,
            226,
            832,
            556,
            197,
            752,
            1164,
            714,
            1094,
            895,
            149,
            396,
            472,
            404,
            583,
            792,
            820,
            628,
            276,
            262,
            584,
            328,
            1053,
            526
        ],
        [
            127,
            766,
            1045,
            998,
            567,
            551,
            593,
            725,
            280,
            608,
            944,
            772,
            532,
            1043,
            356,
            0,
            685,
            1025,
            741,
            935,
            733,
            941,
            164,
            1036,
            928,
            710,
            979,
            197,
            592,
            301,
            231,
            781,
            1183,
            830,
            1088,
            821,
            237,
            213,
            237,
            126,
            603,
            878,
            667,
            381,
            385,
            241,
            476,
            72,
            1058,
            299
        ],
        [
            787,
            341,
            768,
            772,
            833,
            862,
            1045,
            1006,
            903,
            125,
            909,
            1070,
            529,
            927,
            945,
            685,
            0,
            882,
            294,
            1226,
            303,
            854,
            763,
            931,
            563,
            134,
            683,
            876,
            120,
            395,
            903,
            687,
            900,
            863,
            786,
            501,
            890,
            549,
            477,
            572,
            629,
            833,
            296,
            318,
            749,
            685,
            439,
            658,
            787,
            419
        ],
        [
            1016,
            549,
            197,
            137,
            562,
            610,
            801,
            571,
            994,
            779,
            151,
            607,
            504,
            50,
            959,
            1025,
            882,
            0,
            593,
            659,
            581,
            96,
            939,
            62,
            368,
            754,
            247,
            1092,
            801,
            843,
            1089,
            247,
            233,
            257,
            232,
            386,
            1040,
            820,
            839,
            922,
            421,
            167,
            589,
            817,
            698,
            805,
            593,
            953,
            187,
            806
        ],
        [
            808,
            47,
            474,
            478,
            666,
            708,
            918,
            815,
            881,
            216,
            635,
            879,
            354,
            639,
            898,
            741,
            294,
            593,
            0,
            1018,
            16,
            574,
            757,
            645,
            272,
            162,
            389,
            901,
            241,
            449,
            919,
            422,
            608,
            610,
            494,
            207,
            890,
            546,
            504,
            615,
            422,
            563,
            78,
            379,
            646,
            641,
            314,
            690,
            493,
            442
        ],
        [
            848,
            994,
            841,
            766,
            410,
            401,
            378,
            228,
            731,
            1100,
            510,
            168,
            696,
            625,
            653,
            935,
            1226,
            659,
            1018,
            0,
            1002,
            582,
            778,
            609,
            932,
            1138,
            853,
            873,
            1109,
            957,
            848,
            627,
            889,
            445,
            884,
            879,
            796,
            827,
            896,
            905,
            602,
            535,
            965,
            988,
            567,
            708,
            789,
            874,
            836,
            910
        ],
        [
            797,
            42,
            466,
            468,
            650,
            692,
            902,
            799,
            868,
            219,
            622,
            863,
            338,
            627,
            884,
            733,
            303,
            581,
            16,
            1002,
            0,
            560,
            745,
            632,
            267,
            172,
            381,
            890,
            245,
            442,
            908,
            407,
            602,
            595,
            488,
            197,
            878,
            535,
            495,
            606,
            406,
            549,
            66,
            374,
            631,
            628,
            300,
            680,
            485,
            434
        ],
        [
            928,
            533,
            258,
            185,
            466,
            514,
            706,
            479,
            901,
            743,
            76,
            518,
            432,
            101,
            864,
            941,
            854,
            96,
            574,
            582,
            560,
            0,
            849,
            95,
            386,
            730,
            282,
            1001,
            763,
            776,
            997,
            180,
            323,
            162,
            301,
            377,
            947,
            741,
            765,
            843,
            340,
            71,
            558,
            757,
            605,
            717,
            527,
            869,
            254,
            737
        ],
        [
            79,
            773,
            988,
            932,
            432,
            407,
            429,
            576,
            141,
            666,
            840,
            618,
            480,
            950,
            202,
            164,
            763,
            939,
            757,
            778,
            745,
            849,
            0,
            941,
            901,
            761,
            931,
            156,
            655,
            368,
            165,
            706,
            1119,
            721,
            1034,
            795,
            133,
            218,
            285,
            203,
            525,
            781,
            679,
            444,
            253,
            135,
            455,
            125,
            999,
            344
        ],
        [
            1020,
            602,
            260,
            199,
            547,
            594,
            775,
            537,
            988,
            825,
            115,
            569,
            527,
            16,
            948,
            1036,
            931,
            62,
            645,
            609,
            632,
            95,
            941,
            0,
            429,
            804,
            309,
            1092,
            845,
            870,
            1087,
            272,
            280,
            235,
            293,
            440,
            1037,
            836,
            860,
            938,
            435,
            159,
            636,
            849,
            695,
            810,
            621,
            963,
            249,
            831
        ],
        [
            966,
            225,
            209,
            235,
            669,
            719,
            938,
            770,
            1002,
            487,
            460,
            825,
            425,
            419,
            996,
            928,
            563,
            368,
            272,
            932,
            267,
            386,
            901,
            429,
            0,
            429,
            128,
            1056,
            512,
            667,
            1066,
            308,
            337,
            487,
            223,
            107,
            1027,
            716,
            699,
            805,
            423,
            407,
            308,
            611,
            721,
            769,
            453,
            865,
            228,
            646
        ],
        [
            798,
            208,
            634,
            640,
            760,
            795,
            992,
            924,
            896,
            105,
            789,
            989,
            446,
            800,
            927,
            710,
            134,
            754,
            162,
            1138,
            172,
            730,
            761,
            804,
            429,
            0,
            549,
            890,
            126,
            409,
            914,
            570,
            766,
            752,
            652,
            369,
            893,
            543,
            482,
            588,
            536,
            714,
            178,
            329,
            703,
            664,
            372,
            671,
            653,
            419
        ],
        [
            1002,
            342,
            85,
            110,
            642,
            693,
            908,
            715,
            1018,
            597,
            358,
            765,
            452,
            298,
            1002,
            979,
            683,
            247,
            389,
            853,
            381,
            282,
            931,
            309,
            128,
            549,
            0,
            1088,
            622,
            740,
            1094,
            261,
            224,
            409,
            114,
            189,
            1050,
            765,
            760,
            861,
            419,
            318,
            410,
            694,
            725,
            796,
            506,
            912,
            104,
            713
        ],
        [
            93,
            920,
            1144,
            1089,
            567,
            535,
            501,
            690,
            143,
            790,
            989,
            723,
            636,
            1101,
            226,
            197,
            876,
            1092,
            901,
            873,
            890,
            1001,
            156,
            1092,
            1056,
            890,
            1088,
            0,
            776,
            484,
            37,
            862,
            1275,
            867,
            1191,
            950,
            77,
            355,
            408,
            304,
            681,
            932,
            824,
            563,
            398,
            292,
            607,
            218,
            1156,
            471
        ],
        [
            686,
            287,
            707,
            701,
            713,
            742,
            925,
            887,
            793,
            25,
            813,
            951,
            413,
            843,
            832,
            592,
            120,
            801,
            241,
            1109,
            245,
            763,
            655,
            845,
            512,
            126,
            622,
            776,
            0,
            292,
            802,
            590,
            845,
            758,
            731,
            433,
            785,
            439,
            371,
            473,
            516,
            735,
            214,
            213,
            629,
            570,
            320,
            558,
            725,
            310
        ],
        [
            394,
            479,
            816,
            784,
            546,
            558,
            698,
            729,
            509,
            307,
            801,
            789,
            345,
            873,
            556,
            301,
            395,
            843,
            449,
            957,
            442,
            776,
            368,
            870,
            667,
            409,
            740,
            484,
            292,
            0,
            510,
            598,
            959,
            709,
            854,
            563,
            495,
            162,
            83,
            180,
            449,
            725,
            379,
            79,
            408,
            306,
            250,
            265,
            832,
            46
        ],
        [
            116,
            936,
            1148,
            1091,
            556,
            521,
            474,
            671,
            117,
            815,
            982,
            702,
            644,
            1097,
            197,
            231,
            903,
            1089,
            919,
            848,
            908,
            997,
            165,
            1087,
            1066,
            914,
            1094,
            37,
            802,
            510,
            0,
            863,
            1277,
            860,
            1195,
            960,
            53,
            374,
            432,
            331,
            683,
            928,
            841,
            589,
            392,
            298,
            621,
            245,
            1159,
            494
        ],
        [
            782,
            388,
            293,
            229,
            381,
            432,
            647,
            462,
            776,
            572,
            222,
            517,
            257,
            274,
            752,
            781,
            687,
            247,
            422,
            627,
            407,
            180,
            706,
            272,
            308,
            570,
            261,
            862,
            590,
            598,
            863,
            0,
            414,
            191,
            342,
            253,
            816,
            574,
            592,
            676,
            180,
            145,
            393,
            577,
            479,
            570,
            348,
            710,
            301,
            560
        ],
        [
            1193,
            561,
            143,
            186,
            777,
            827,
            1027,
            802,
            1191,
            821,
            384,
            840,
            651,
            264,
            1164,
            1183,
            900,
            233,
            608,
            889,
            602,
            323,
            1119,
            280,
            337,
            766,
            224,
            1275,
            845,
            959,
            1277,
            414,
            0,
            486,
            114,
            414,
            1230,
            971,
            973,
            1069,
            594,
            390,
            634,
            916,
            893,
            983,
            718,
            1113,
            127,
            930
        ],
        [
            800,
            578,
            407,
            332,
            313,
            359,
            544,
            317,
            758,
            742,
            123,
            360,
            370,
            248,
            714,
            830,
            863,
            257,
            610,
            445,
            595,
            162,
            721,
            235,
            487,
            752,
            409,
            867,
            758,
            709,
            860,
            191,
            486,
            0,
            454,
            443,
            808,
            643,
            682,
            744,
            261,
            97,
            574,
            706,
            469,
            595,
            474,
            758,
            406,
            666
        ],
        [
            1106,
            447,
            49,
            122,
            720,
            771,
            980,
            770,
            1115,
            706,
            374,
            814,
            558,
            278,
            1094,
            1088,
            786,
            232,
            494,
            884,
            488,
            301,
            1034,
            293,
            223,
            652,
            114,
            1191,
            731,
            854,
            1195,
            342,
            114,
            454,
            0,
            301,
            1150,
            875,
            873,
            972,
            514,
            357,
            521,
            808,
            819,
            898,
            617,
            1020,
            48,
            826
        ],
        [
            860,
            162,
            273,
            270,
            584,
            633,
            852,
            700,
            898,
            410,
            444,
            759,
            321,
            434,
            895,
            821,
            501,
            386,
            207,
            879,
            197,
            377,
            795,
            440,
            107,
            369,
            189,
            950,
            433,
            563,
            960,
            253,
            414,
            443,
            301,
            0,
            922,
            609,
            593,
            699,
            333,
            379,
            221,
            511,
            622,
            664,
            346,
            758,
            291,
            541
        ],
        [
            110,
            905,
            1103,
            1044,
            503,
            467,
            423,
            617,
            66,
            797,
            931,
            649,
            603,
            1047,
            149,
            237,
            890,
            1040,
            890,
            796,
            878,
            947,
            133,
            1037,
            1027,
            893,
            1050,
            77,
            785,
            495,
            53,
            816,
            1230,
            808,
            1150,
            922,
            0,
            350,
            414,
            320,
            637,
            878,
            812,
            573,
            341,
            258,
            586,
            235,
            1113,
            475
        ],
        [
            262,
            565,
            832,
            786,
            424,
            425,
            543,
            602,
            354,
            448,
            751,
            659,
            320,
            841,
            396,
            213,
            549,
            820,
            546,
            827,
            535,
            741,
            218,
            836,
            716,
            543,
            765,
            355,
            439,
            162,
            374,
            574,
            971,
            643,
            875,
            609,
            350,
            0,
            80,
            102,
            400,
            680,
            468,
            232,
            262,
            145,
            263,
            149,
            846,
            130
        ],
        [
            316,
            529,
            832,
            792,
            489,
            495,
            622,
            669,
            426,
            383,
            783,
            728,
            334,
            865,
            472,
            237,
            477,
            839,
            504,
            896,
            495,
            765,
            285,
            860,
            699,
            482,
            760,
            408,
            371,
            83,
            432,
            592,
            973,
            682,
            873,
            593,
            414,
            80,
            0,
            111,
            428,
            709,
            429,
            158,
            337,
            225,
            255,
            190,
            847,
            62
        ],
        [
            215,
            640,
            929,
            886,
            512,
            506,
            595,
            684,
            344,
            487,
            852,
            738,
            421,
            944,
            404,
            126,
            572,
            922,
            615,
            905,
            606,
            843,
            203,
            938,
            805,
            588,
            861,
            304,
            473,
            180,
            331,
            676,
            1069,
            744,
            972,
            699,
            320,
            102,
            111,
            0,
            502,
            782,
            540,
            259,
            338,
            199,
            355,
            86,
            943,
            173
        ],
        [
            601,
            405,
            466,
            407,
            253,
            300,
            519,
            393,
            601,
            504,
            354,
            457,
            109,
            441,
            583,
            603,
            629,
            421,
            422,
            602,
            406,
            340,
            525,
            435,
            423,
            536,
            419,
            681,
            516,
            449,
            683,
            180,
            594,
            261,
            514,
            333,
            637,
            400,
            428,
            502,
            0,
            281,
            364,
            445,
            306,
            390,
            214,
            531,
            476,
            406
        ],
        [
            860,
            526,
            311,
            236,
            395,
            443,
            637,
            414,
            830,
            717,
            78,
            457,
            380,
            169,
            792,
            878,
            833,
            167,
            563,
            535,
            549,
            71,
            781,
            159,
            407,
            714,
            318,
            932,
            735,
            725,
            928,
            145,
            390,
            97,
            357,
            379,
            878,
            680,
            709,
            782,
            281,
            0,
            538,
            712,
            536,
            651,
            480,
            805,
            309,
            685
        ],
        [
            731,
            100,
            494,
            487,
            601,
            640,
            847,
            756,
            802,
            191,
            613,
            820,
            285,
            633,
            820,
            667,
            296,
            589,
            78,
            965,
            66,
            558,
            679,
            636,
            308,
            178,
            410,
            824,
            214,
            379,
            841,
            393,
            634,
            574,
            521,
            221,
            812,
            468,
            429,
            540,
            364,
            538,
            0,
            313,
            571,
            563,
            237,
            613,
            512,
            369
        ],
        [
            473,
            413,
            773,
            746,
            578,
            596,
            752,
            760,
            584,
            227,
            789,
            822,
            336,
            850,
            628,
            381,
            318,
            817,
            379,
            988,
            374,
            757,
            444,
            849,
            611,
            329,
            694,
            563,
            213,
            79,
            589,
            577,
            916,
            706,
            808,
            511,
            573,
            232,
            158,
            259,
            445,
            712,
            313,
            0,
            457,
            372,
            232,
            344,
            790,
            102
        ],
        [
            333,
            647,
            771,
            709,
            182,
            168,
            296,
            346,
            297,
            630,
            591,
            399,
            304,
            705,
            276,
            385,
            749,
            698,
            646,
            567,
            631,
            605,
            253,
            695,
            721,
            703,
            725,
            398,
            629,
            408,
            392,
            479,
            893,
            469,
            819,
            622,
            341,
            262,
            337,
            338,
            306,
            536,
            571,
            457,
            0,
            145,
            335,
            317,
            780,
            364
        ],
        [
            211,
            652,
            852,
            796,
            326,
            313,
            401,
            490,
            240,
            577,
            712,
            541,
            345,
            818,
            262,
            241,
            685,
            805,
            641,
            708,
            628,
            717,
            135,
            810,
            769,
            664,
            796,
            292,
            570,
            306,
            298,
            570,
            983,
            595,
            898,
            664,
            258,
            145,
            225,
            199,
            390,
            651,
            563,
            372,
            145,
            0,
            331,
            172,
            863,
            270
        ],
        [
            516,
            321,
            576,
            538,
            393,
            425,
            620,
            567,
            571,
            314,
            557,
            631,
            104,
            623,
            584,
            476,
            439,
            593,
            314,
            789,
            300,
            527,
            455,
            621,
            453,
            372,
            506,
            607,
            320,
            250,
            621,
            348,
            718,
            474,
            617,
            346,
            586,
            263,
            255,
            355,
            214,
            480,
            237,
            232,
            335,
            331,
            0,
            412,
            591,
            214
        ],
        [
            129,
            712,
            976,
            928,
            498,
            484,
            543,
            660,
            262,
            571,
            871,
            709,
            462,
            970,
            328,
            72,
            658,
            953,
            690,
            874,
            680,
            869,
            125,
            963,
            865,
            671,
            912,
            218,
            558,
            265,
            245,
            710,
            1113,
            758,
            1020,
            758,
            235,
            149,
            190,
            86,
            531,
            805,
            613,
            344,
            317,
            172,
            412,
            0,
            989,
            253
        ],
        [
            1072,
            446,
            19,
            75,
            676,
            727,
            934,
            722,
            1076,
            701,
            326,
            767,
            526,
            234,
            1053,
            1058,
            787,
            187,
            493,
            836,
            485,
            254,
            999,
            249,
            228,
            653,
            104,
            1156,
            725,
            832,
            1159,
            301,
            127,
            406,
            48,
            291,
            1113,
            846,
            847,
            943,
            476,
            309,
            512,
            790,
            780,
            863,
            591,
            989,
            0,
            803
        ],
        [
            379,
            469,
            787,
            752,
            500,
            512,
            656,
            682,
            483,
            322,
            760,
            743,
            304,
            834,
            526,
            299,
            419,
            806,
            442,
            910,
            434,
            737,
            344,
            831,
            646,
            419,
            713,
            471,
            310,
            46,
            494,
            560,
            930,
            666,
            826,
            541,
            475,
            130,
            62,
            173,
            406,
            685,
            369,
            102,
            364,
            270,
            214,
            253,
            803,
            0
        ]
    ]
}