{
    "config": {
        "max_coordinate": 1000
    },
    "nodes": 50,
    "node_positions": [
        [
            514,
            370
        ],
        [
            124,
            471
        ],
        [
            742,
            136
        ],
        [
            198,
            454
        ],
        [
            644,
            220
        ],
        [
            626,
            611
        ],
        [
            977,
            341
        ],
        [
            150,
            209
        ],
        [
            479,
            61
        ],
        [
            867,
            127
        ],
        [
            425,
            172
        ],
        [
            850,
            968
        ],
        [
            474,
            165
        ],
        [
            628,
            650
        ],
        [
            63,
            186
        ],
        [
            940,
            282
        ],
        [
            533,
            260
        ],
        [
            482,
            187
        ],
        [
            251,
            221
        ],
        [
            941,
            832
        ],
        [
            861,
            964
        ],
        [
            505,
            204
        ],
        [
            777,
            541
        ],
        [
            397,
            534
        ],
        [
            714,
            936
        ],
        [
            537,
            428
        ],
        [
            181,
            509
        ],
        [
            353,
            161
        ],
        [
            361,
            238
        ],
        [
            191,
            590
        ],
        [
            696,
            982
        ],
        [
            113,
            683
        ],
        [
            74,
            703
        ],
        [
            699,
            50
        ],
        [
            746,
            873
        ],
        [
            683,
            902
        ],
        [
            254,
            548
        ],
        [
            855,
            383
        ],
        [
            261,
            584
        ],
        [
            558,
            575
        ],
        [
            876,
            119
        ],
        [
            80,
            499
        ],
        [
            999,
            662
        ],
        [
            57,
            842
        ],
        [
            392,
            48
        ],
        [
            77,
            759
        ],
        [
            789,
            703
        ],
        [
            656,
            79
        ],
        [
            460,
            88
        ],
        [
            239,
            995
        ]
    ],
    "dist": [
        [
            0,
            402,
            326,
            326,
            198,
            265,
            463,
            398,
            310,
            428,
            217,
            685,
            208,
            302,
            487,
            434,
            111,
            185,
            302,
            629,
            687,
            166,
            313,
            201,
            600,
            62,
            360,
            263,
            202,
            390,
            638,
            508,
            551,
            369,
            553,
            558,
            315,
            341,
            331,
            209,
            440,
            452,
            566,
            656,
            344,
            585,
            431,
            323,
            287,
            682
        ],
        [
            402,
            0,
            702,
            75,
            577,
            521,
            862,
            263,
            542,
            818,
            424,
            879,
            464,
            534,
            291,
            837,
            460,
            456,
            280,
            893,
            886,
            465,
            656,
            280,
            751,
            415,
            68,
            385,
            332,
            136,
            767,
            212,
            237,
            712,
            740,
            705,
            151,
            736,
            177,
            446,
            830,
            52,
            895,
            377,
            500,
            291,
            704,
            660,
            509,
            536
        ],
        [
            326,
            702,
            0,
            630,
            129,
            488,
            311,
            596,
            273,
            125,
            319,
            838,
            269,
            526,
            680,
            246,
            243,
            264,
            498,
            723,
            836,
            246,
            406,
            526,
            800,
            356,
            673,
            389,
            394,
            713,
            847,
            833,
            876,
            96,
            737,
            768,
            638,
            271,
            657,
            476,
            135,
            754,
            585,
            983,
            360,
            911,
            568,
            103,
            286,
            995
        ],
        [
            326,
            75,
            630,
            0,
            503,
            455,
            787,
            249,
            483,
            744,
            362,
            830,
            399,
            472,
            300,
            761,
            387,
            389,
            238,
            833,
            836,
            395,
            585,
            214,
            706,
            339,
            57,
            331,
            270,
            136,
            725,
            244,
            278,
            643,
            689,
            660,
            109,
            660,
            144,
            379,
            756,
            126,
            827,
            412,
            449,
            328,
            641,
            591,
            450,
            542
        ],
        [
            198,
            577,
            129,
            503,
            0,
            391,
            354,
            494,
            229,
            241,
            224,
            775,
            178,
            430,
            581,
            302,
            117,
            165,
            393,
            680,
            775,
            139,
            347,
            399,
            719,
            233,
            545,
            296,
            283,
            584,
            763,
            704,
            747,
            178,
            660,
            683,
            509,
            266,
            528,
            365,
            253,
            629,
            566,
            855,
            305,
            782,
            504,
            141,
            226,
            874
        ],
        [
            265,
            521,
            488,
            455,
            391,
            0,
            442,
            623,
            569,
            540,
            482,
            421,
            471,
            39,
            705,
            454,
            363,
            447,
            541,
            384,
            424,
            424,
            166,
            241,
            336,
            203,
            456,
            526,
            457,
            435,
            377,
            518,
            559,
            565,
            288,
            296,
            377,
            323,
            365,
            76,
            551,
            557,
            376,
            614,
            609,
            568,
            187,
            532,
            548,
            545
        ],
        [
            463,
            862,
            311,
            787,
            354,
            442,
            0,
            837,
            571,
            240,
            577,
            639,
            532,
            466,
            927,
            69,
            451,
            518,
            735,
            492,
            633,
            491,
            282,
            611,
            650,
            448,
            813,
            649,
            624,
            824,
            699,
            929,
            972,
            402,
            579,
            633,
            752,
            129,
            756,
            479,
            243,
            910,
            321,
            1047,
            654,
            992,
            407,
            414,
            575,
            986
        ],
        [
            398,
            263,
            596,
            249,
            494,
            623,
            837,
            0,
            360,
            721,
            277,
            1032,
            326,
            650,
            89,
            793,
            386,
            332,
            101,
            1006,
            1037,
            355,
            709,
            408,
            920,
            444,
            301,
            208,
            212,
            383,
            946,
            475,
            499,
            571,
            892,
            874,
            354,
            726,
            391,
            548,
            731,
            298,
            962,
            639,
            290,
            554,
            807,
            522,
            332,
            791
        ],
        [
            310,
            542,
            273,
            483,
            229,
            569,
            571,
            360,
            0,
            393,
            123,
            979,
            104,
            607,
            434,
            511,
            206,
            126,
            278,
            898,
            980,
            145,
            564,
            480,
            906,
            371,
            538,
            160,
            212,
            602,
            946,
            721,
            759,
            220,
            854,
            865,
            536,
            495,
            566,
            520,
            401,
            592,
            794,
            887,
            87,
            805,
            712,
            177,
            33,
            964
        ],
        [
            428,
            818,
            125,
            744,
            241,
            540,
            240,
            721,
            393,
            0,
            444,
            841,
            394,
            575,
            806,
            171,
            359,
            389,
            623,
            708,
            837,
            370,
            423,
            621,
            823,
            446,
            785,
            515,
            518,
            819,
            871,
            936,
            980,
            184,
            755,
            796,
            743,
            256,
            759,
            544,
            12,
            870,
            551,
            1080,
            481,
            1011,
            581,
            216,
            408,
            1071
        ],
        [
            217,
            424,
            319,
            362,
            224,
            482,
            577,
            277,
            123,
            444,
            0,
            902,
            49,
            519,
            362,
            526,
            139,
            58,
            180,
            837,
            904,
            86,
            509,
            363,
            816,
            279,
            416,
            72,
            91,
            479,
            854,
            598,
            636,
            299,
            771,
            774,
            413,
            478,
            443,
            424,
            454,
            475,
            754,
            764,
            128,
            682,
            643,
            249,
            91,
            843
        ],
        [
            685,
            879,
            838,
            830,
            775,
            421,
            639,
            1032,
            979,
            841,
            902,
            0,
            886,
            387,
            1109,
            691,
            775,
            863,
            957,
            163,
            11,
            838,
            433,
            627,
            139,
            624,
            811,
            947,
            878,
            759,
            154,
            790,
            820,
            930,
            140,
            179,
            729,
            585,
            703,
            489,
            849,
            901,
            340,
            802,
            1027,
            800,
            271,
            909,
            962,
            611
        ],
        [
            208,
            464,
            269,
            399,
            178,
            471,
            532,
            326,
            104,
            394,
            49,
            886,
            0,
            508,
            411,
            480,
            111,
            23,
            229,
            814,
            887,
            49,
            482,
            376,
            807,
            270,
            451,
            121,
            134,
            510,
            846,
            631,
            670,
            252,
            758,
            766,
            441,
            438,
            470,
            418,
            404,
            516,
            722,
            795,
            142,
            714,
            623,
            201,
            78,
            862
        ],
        [
            302,
            534,
            526,
            472,
            430,
            39,
            466,
            650,
            607,
            575,
            519,
            387,
            508,
            0,
            731,
            482,
            401,
            485,
            571,
            362,
            391,
            462,
            184,
            258,
            298,
            239,
            468,
            561,
            490,
            441,
            338,
            516,
            556,
            604,
            252,
            257,
            387,
            350,
            372,
            102,
            586,
            568,
            371,
            602,
            646,
            561,
            169,
            571,
            586,
            519
        ],
        [
            487,
            291,
            680,
            300,
            581,
            705,
            927,
            89,
            434,
            806,
            362,
            1109,
            411,
            731,
            0,
            882,
            475,
            419,
            191,
            1090,
            1114,
            442,
            797,
            482,
            993,
            532,
            343,
            291,
            302,
            423,
            1017,
            499,
            517,
            650,
            968,
            947,
            409,
            816,
            444,
            629,
            815,
            313,
            1050,
            656,
            356,
            573,
            891,
            602,
            408,
            827
        ],
        [
            434,
            837,
            246,
            761,
            302,
            454,
            69,
            793,
            511,
            171,
            526,
            691,
            480,
            482,
            882,
            0,
            407,
            467,
            691,
            550,
            686,
            441,
            306,
            598,
            691,
            428,
            792,
            599,
            580,
            809,
            741,
            919,
            962,
            334,
            622,
            671,
            735,
            132,
            743,
            481,
            175,
            886,
            384,
            1045,
            595,
            986,
            447,
            349,
            517,
            999
        ],
        [
            111,
            460,
            243,
            387,
            117,
            363,
            451,
            386,
            206,
            359,
            139,
            775,
            111,
            401,
            475,
            407,
            0,
            89,
            284,
            702,
            776,
            62,
            372,
            305,
            699,
            168,
            431,
            205,
            173,
            475,
            740,
            596,
            637,
            267,
            648,
            659,
            400,
            344,
            423,
            315,
            370,
            512,
            615,
            751,
            254,
            675,
            511,
            218,
            186,
            791
        ],
        [
            185,
            456,
            264,
            389,
            165,
            447,
            518,
            332,
            126,
            389,
            58,
            863,
            23,
            485,
            419,
            467,
            89,
            0,
            233,
            791,
            864,
            28,
            460,
            357,
            784,
            247,
            440,
            131,
            131,
            497,
            823,
            618,
            657,
            256,
            735,
            742,
            426,
            421,
            454,
            395,
            399,
            508,
            702,
            780,
            165,
            700,
            600,
            204,
            101,
            843
        ],
        [
            302,
            280,
            498,
            238,
            393,
            541,
            735,
            101,
            278,
            623,
            180,
            957,
            229,
            571,
            191,
            691,
            284,
            233,
            0,
            921,
            961,
            254,
            615,
            345,
            851,
            353,
            296,
            118,
            111,
            373,
            881,
            482,
            513,
            479,
            818,
            806,
            327,
            625,
            363,
            468,
            633,
            326,
            868,
            650,
            223,
            565,
            722,
            429,
            247,
            774
        ],
        [
            629,
            893,
            723,
            833,
            680,
            384,
            492,
            1006,
            898,
            708,
            837,
            163,
            814,
            362,
            1090,
            550,
            702,
            791,
            921,
            0,
            154,
            764,
            334,
            620,
            249,
            571,
            825,
            892,
            830,
            788,
            287,
            841,
            876,
            818,
            199,
            267,
            743,
            457,
            723,
            461,
            715,
            923,
            179,
            884,
            957,
            867,
            199,
            805,
            885,
            720
        ],
        [
            687,
            886,
            836,
            836,
            775,
            424,
            633,
            1037,
            980,
            837,
            904,
            11,
            887,
            391,
            1114,
            686,
            776,
            864,
            961,
            154,
            0,
            839,
            431,
            632,
            149,
            626,
            818,
            950,
            881,
            767,
            165,
            799,
            829,
            928,
            146,
            188,
            735,
            581,
            710,
            493,
            845,
            908,
            332,
            813,
            1029,
            810,
            270,
            908,
            963,
            622
        ],
        [
            166,
            465,
            246,
            395,
            139,
            424,
            491,
            355,
            145,
            370,
            86,
            838,
            49,
            462,
            442,
            441,
            62,
            28,
            254,
            764,
            839,
            0,
            433,
            347,
            761,
            226,
            444,
            157,
            147,
            497,
            801,
            618,
            659,
            247,
            711,
            720,
            425,
            393,
            451,
            374,
            380,
            517,
            673,
            779,
            192,
            700,
            574,
            196,
            124,
            834
        ],
        [
            313,
            656,
            406,
            585,
            347,
            166,
            282,
            709,
            564,
            423,
            509,
            433,
            482,
            184,
            797,
            306,
            372,
            460,
            615,
            334,
            431,
            433,
            0,
            380,
            399,
            265,
            596,
            569,
            514,
            588,
            448,
            679,
            721,
            497,
            333,
            373,
            523,
            176,
            517,
            221,
            433,
            698,
            252,
            780,
            625,
            733,
            162,
            477,
            552,
            703
        ],
        [
            201,
            280,
            526,
            214,
            399,
            241,
            611,
            408,
            480,
            621,
            363,
            627,
            376,
            258,
            482,
            598,
            305,
            357,
            345,
            620,
            632,
            347,
            380,
            0,
            511,
            175,
            217,
            375,
            298,
            213,
            538,
            320,
            364,
            570,
            486,
            466,
            143,
            482,
            144,
            166,
            633,
            318,
            615,
            458,
            486,
            391,
            426,
            523,
            450,
            487
        ],
        [
            600,
            751,
            800,
            706,
            719,
            336,
            650,
            920,
            906,
            823,
            816,
            139,
            807,
            298,
            993,
            691,
            699,
            784,
            851,
            249,
            149,
            761,
            399,
            511,
            0,
            537,
            682,
            854,
            782,
            627,
            49,
            652,
            681,
            886,
            70,
            46,
            601,
            570,
            573,
            393,
            832,
            770,
            395,
            663,
            944,
            661,
            244,
            858,
            885,
            478
        ],
        [
            62,
            415,
            356,
            339,
            233,
            203,
            448,
            444,
            371,
            446,
            279,
            624,
            270,
            239,
            532,
            428,
            168,
            247,
            353,
            571,
            626,
            226,
            265,
            175,
            537,
            0,
            365,
            324,
            258,
            382,
            576,
            494,
            538,
            411,
            491,
            495,
            307,
            321,
            317,
            148,
            458,
            462,
            517,
            633,
            406,
            566,
            373,
            368,
            348,
            640
        ],
        [
            360,
            68,
            673,
            57,
            545,
            456,
            813,
            301,
            538,
            785,
            416,
            811,
            451,
            468,
            343,
            792,
            431,
            440,
            296,
            825,
            818,
            444,
            596,
            217,
            682,
            365,
            0,
            388,
            325,
            81,
            699,
            186,
            221,
            692,
            672,
            637,
            82,
            685,
            109,
            382,
            796,
            101,
            832,
            355,
            506,
            270,
            638,
            640,
            505,
            489
        ],
        [
            263,
            385,
            389,
            331,
            296,
            526,
            649,
            208,
            160,
            515,
            72,
            947,
            121,
            561,
            291,
            599,
            205,
            131,
            118,
            892,
            950,
            157,
            569,
            375,
            854,
            324,
            388,
            0,
            77,
            458,
            889,
            574,
            609,
            363,
            813,
            811,
            399,
            548,
            432,
            461,
            524,
            434,
            817,
            742,
            119,
            658,
            695,
            313,
            129,
            841
        ],
        [
            202,
            332,
            394,
            270,
            283,
            457,
            624,
            212,
            212,
            518,
            91,
            878,
            134,
            490,
            302,
            580,
            173,
            131,
            111,
            830,
            881,
            147,
            514,
            298,
            782,
            258,
            325,
            77,
            0,
            390,
            815,
            509,
            546,
            386,
            742,
            737,
            327,
            514,
            360,
            390,
            528,
            383,
            766,
            676,
            192,
            593,
            631,
            335,
            179,
            766
        ],
        [
            390,
            136,
            713,
            136,
            584,
            435,
            824,
            383,
            602,
            819,
            479,
            759,
            510,
            441,
            423,
            809,
            475,
            497,
            373,
            788,
            767,
            497,
            588,
            213,
            627,
            382,
            81,
            458,
            390,
            0,
            639,
            121,
            162,
            741,
            622,
            582,
            75,
            695,
            70,
            367,
            831,
            143,
            811,
            285,
            578,
            203,
            608,
            690,
            569,
            407
        ],
        [
            638,
            767,
            847,
            725,
            763,
            377,
            699,
            946,
            946,
            871,
            854,
            154,
            846,
            338,
            1017,
            741,
            740,
            823,
            881,
            287,
            165,
            801,
            448,
            538,
            49,
            576,
            699,
            889,
            815,
            639,
            0,
            655,
            681,
            932,
            119,
            81,
            619,
            619,
            589,
            429,
            881,
            782,
            440,
            654,
            982,
            657,
            294,
            903,
            924,
            457
        ],
        [
            508,
            212,
            833,
            244,
            704,
            518,
            929,
            475,
            721,
            936,
            598,
            790,
            631,
            516,
            499,
            919,
            596,
            618,
            482,
            841,
            799,
            618,
            679,
            320,
            652,
            494,
            186,
            574,
            509,
            121,
            655,
            0,
            43,
            862,
            660,
            610,
            195,
            800,
            178,
            457,
            948,
            186,
            886,
            168,
            693,
            84,
            676,
            812,
            688,
            336
        ],
        [
            551,
            237,
            876,
            278,
            747,
            559,
            972,
            499,
            759,
            980,
            636,
            820,
            670,
            556,
            517,
            962,
            637,
            657,
            513,
            876,
            829,
            659,
            721,
            364,
            681,
            538,
            221,
            609,
            546,
            162,
            681,
            43,
            0,
            903,
            693,
            640,
            237,
            844,
            221,
            500,
            992,
            204,
            925,
            140,
            728,
            56,
            715,
            853,
            726,
            335
        ],
        [
            369,
            712,
            96,
            643,
            178,
            565,
            402,
            571,
            220,
            184,
            299,
            930,
            252,
            604,
            650,
            334,
            267,
            256,
            479,
            818,
            928,
            247,
            497,
            570,
            886,
            411,
            692,
            363,
            386,
            741,
            932,
            862,
            903,
            0,
            824,
            852,
            667,
            367,
            690,
            543,
            189,
            764,
            681,
            1019,
            307,
            943,
            659,
            51,
            242,
            1051
        ],
        [
            553,
            740,
            737,
            689,
            660,
            288,
            579,
            892,
            854,
            755,
            771,
            140,
            758,
            252,
            968,
            622,
            648,
            735,
            818,
            199,
            146,
            711,
            333,
            486,
            70,
            491,
            672,
            813,
            742,
            622,
            119,
            660,
            693,
            824,
            0,
            69,
            589,
            501,
            564,
            352,
            765,
            763,
            329,
            689,
            897,
            678,
            175,
            799,
            835,
            521
        ],
        [
            558,
            705,
            768,
            660,
            683,
            296,
            633,
            874,
            865,
            796,
            774,
            179,
            766,
            257,
            947,
            671,
            659,
            742,
            806,
            267,
            188,
            720,
            373,
            466,
            46,
            495,
            637,
            811,
            737,
            582,
            81,
            610,
            640,
            852,
            69,
            0,
            556,
            546,
            528,
            350,
            806,
            725,
            396,
            628,
            902,
            622,
            225,
            823,
            843,
            453
        ],
        [
            315,
            151,
            638,
            109,
            509,
            377,
            752,
            354,
            536,
            743,
            413,
            729,
            441,
            387,
            409,
            735,
            400,
            426,
            327,
            743,
            735,
            425,
            523,
            143,
            601,
            307,
            82,
            399,
            327,
            75,
            619,
            195,
            237,
            667,
            589,
            556,
            0,
            623,
            36,
            305,
            755,
            180,
            753,
            353,
            518,
            275,
            557,
            617,
            504,
            447
        ],
        [
            341,
            736,
            271,
            660,
            266,
            323,
            129,
            726,
            495,
            256,
            478,
            585,
            438,
            350,
            816,
            132,
            344,
            421,
            625,
            457,
            581,
            393,
            176,
            482,
            570,
            321,
            685,
            548,
            514,
            695,
            619,
            800,
            844,
            367,
            501,
            546,
            623,
            0,
            627,
            353,
            264,
            783,
            313,
            920,
            571,
            864,
            326,
            363,
            493,
            868
        ],
        [
            331,
            177,
            657,
            144,
            528,
            365,
            756,
            391,
            566,
            759,
            443,
            703,
            470,
            372,
            444,
            743,
            423,
            454,
            363,
            723,
            710,
            451,
            517,
            144,
            573,
            317,
            109,
            432,
            360,
            70,
            589,
            178,
            221,
            690,
            564,
            528,
            36,
            627,
            0,
            297,
            771,
            199,
            742,
            328,
            551,
            253,
            541,
            641,
            534,
            411
        ],
        [
            209,
            446,
            476,
            379,
            365,
            76,
            479,
            548,
            520,
            544,
            424,
            489,
            418,
            102,
            629,
            481,
            315,
            395,
            468,
            461,
            493,
            374,
            221,
            166,
            393,
            148,
            382,
            461,
            390,
            367,
            429,
            457,
            500,
            543,
            352,
            350,
            305,
            353,
            297,
            0,
            555,
            484,
            449,
            567,
            552,
            514,
            264,
            505,
            496,
            527
        ],
        [
            440,
            830,
            135,
            756,
            253,
            551,
            243,
            731,
            401,
            12,
            454,
            849,
            404,
            586,
            815,
            175,
            370,
            399,
            633,
            715,
            845,
            380,
            433,
            633,
            832,
            458,
            796,
            524,
            528,
            831,
            881,
            948,
            992,
            189,
            765,
            806,
            755,
            264,
            771,
            555,
            0,
            882,
            556,
            1092,
            489,
            1023,
            590,
            223,
            417,
            1083
        ],
        [
            452,
            52,
            754,
            126,
            629,
            557,
            910,
            298,
            592,
            870,
            475,
            901,
            516,
            568,
            313,
            886,
            512,
            508,
            326,
            923,
            908,
            517,
            698,
            318,
            770,
            462,
            101,
            434,
            383,
            143,
            782,
            186,
            204,
            764,
            763,
            725,
            180,
            783,
            199,
            484,
            882,
            0,
            933,
            343,
            548,
            260,
            737,
            712,
            559,
            520
        ],
        [
            566,
            895,
            585,
            827,
            566,
            376,
            321,
            962,
            794,
            551,
            754,
            340,
            722,
            371,
            1050,
            384,
            615,
            702,
            868,
            179,
            332,
            673,
            252,
            615,
            395,
            517,
            832,
            817,
            766,
            811,
            440,
            886,
            925,
            681,
            329,
            396,
            753,
            313,
            742,
            449,
            556,
            933,
            0,
            959,
            863,
            927,
            213,
            676,
            787,
            829
        ],
        [
            656,
            377,
            983,
            412,
            855,
            614,
            1047,
            639,
            887,
            1080,
            764,
            802,
            795,
            602,
            656,
            1045,
            751,
            780,
            650,
            884,
            813,
            779,
            780,
            458,
            663,
            633,
            355,
            742,
            676,
            285,
            654,
            168,
            140,
            1019,
            689,
            628,
            353,
            920,
            328,
            567,
            1092,
            343,
            959,
            0,
            861,
            85,
            745,
            970,
            854,
            237
        ],
        [
            344,
            500,
            360,
            449,
            305,
            609,
            654,
            290,
            87,
            481,
            128,
            1027,
            142,
            646,
            356,
            595,
            254,
            165,
            223,
            957,
            1029,
            192,
            625,
            486,
            944,
            406,
            506,
            119,
            192,
            578,
            982,
            693,
            728,
            307,
            897,
            902,
            518,
            571,
            551,
            552,
            489,
            548,
            863,
            861,
            0,
            777,
            765,
            265,
            78,
            959
        ],
        [
            585,
            291,
            911,
            328,
            782,
            568,
            992,
            554,
            805,
            1011,
            682,
            800,
            714,
            561,
            573,
            986,
            675,
            700,
            565,
            867,
            810,
            700,
            733,
            391,
            661,
            566,
            270,
            658,
            593,
            203,
            657,
            84,
            56,
            943,
            678,
            622,
            275,
            864,
            253,
            514,
            1023,
            260,
            927,
            85,
            777,
            0,
            714,
            893,
            772,
            286
        ],
        [
            431,
            704,
            568,
            641,
            504,
            187,
            407,
            807,
            712,
            581,
            643,
            271,
            623,
            169,
            891,
            447,
            511,
            600,
            722,
            199,
            270,
            574,
            162,
            426,
            244,
            373,
            638,
            695,
            631,
            608,
            294,
            676,
            715,
            659,
            175,
            225,
            557,
            326,
            541,
            264,
            590,
            737,
            213,
            745,
            765,
            714,
            0,
            638,
            697,
            622
        ],
        [
            323,
            660,
            103,
            591,
            141,
            532,
            414,
            522,
            177,
            216,
            249,
            909,
            201,
            571,
            602,
            349,
            218,
            204,
            429,
            805,
            908,
            196,
            477,
            523,
            858,
            368,
            640,
            313,
            335,
            690,
            903,
            812,
            853,
            51,
            799,
            823,
            617,
            363,
            641,
            505,
            223,
            712,
            676,
            970,
            265,
            893,
            638,
            0,
            196,
            1006
        ],
        [
            287,
            509,
            286,
            450,
            226,
            548,
            575,
            332,
            33,
            408,
            91,
            962,
            78,
            586,
            408,
            517,
            186,
            101,
            247,
            885,
            963,
            124,
            552,
            450,
            885,
            348,
            505,
            129,
            179,
            569,
            924,
            688,
            726,
            242,
            835,
            843,
            504,
            493,
            534,
            496,
            417,
            559,
            787,
            854,
            78,
            772,
            697,
            196,
            0,
            933
        ],
        [
            682,
            536,
            995,
            542,
            874,
            545,
            986,
            791,
            964,
            1071,
            843,
            611,
            862,
            519,
            827,
            999,
            791,
            843,
            774,
            720,
            622,
            834,
            703,
            487,
            478,
            640,
            489,
            841,
            766,
            407,
            457,
            336,
            335,
            1051,
            521,
            453,
            447,
            868,
            411,
            527,
            1083,
            520,
            829,
            237,
            959,
            286,
            622,
            1006,
            933,
            0
        ]
    ]
}